Workbook
Name a: '[2]main menu'!$H$4
Name ACD: '[4]data - main'!$AN$4
Name active_forex: '[4]info - forex'!$J$9
Name as: '[2]main menu'!$H$4
Name availability: '[4]data - PB avail'!$E$5:$AB$508
Name bt_did_mrp: '[4]quote - site BT services'!$Q$18:$Q$217
Name bt_did_otp: '[4]quote - site BT services'!$N$18:$N$217
Name bt_did_zone: '[4]quote - site BT services'!$AQ$18:$AQ$217
Name bt_req_did_mrp: '[4]quote - site BT services'!$R$18:$R$217
Name ccccccccccccc: #REF!
Name CM_free_move_price: IFERROR(VLOOKUP('[4]quote - usage pricing'!XCD1,'[4]data - PB Free Move'!$A:$P,14,FALSE)*active_forex,"")
Name confidential: '[5]main menu'!$B$33
Name connection_type: '[4]data - main'!$AA$4:$AA$10
Name contract_duration: '[4]data - main'!$AJ$3:$AJ$9
Name cost_pbDID1: #REF!
Name cost_pbDID1: #REF!
Name cost_pbDID1: #REF!
Name cost_pbDID1: #REF!
Name cost_pbDID1: #REF!
Name cost_pbDID2: #REF!
Name cost_pbDID2: #REF!
Name cost_pbDID2: #REF!
Name cost_pbDID2: #REF!
Name cost_pbDID2: #REF!
Name cost_pbVAS1: #REF!
Name cost_pbVAS1: #REF!
Name cost_pbVAS1: #REF!
Name cost_pbVAS1: #REF!
Name cost_pbVAS1: #REF!
Name cost_pbVAS2: #REF!
Name cost_pbVAS2: #REF!
Name cost_pbVAS2: #REF!
Name cost_pbVAS2: #REF!
Name cost_pbVAS2: #REF!
Name cost_pbVAS3: #REF!
Name cost_pbVAS3: #REF!
Name cost_pbVAS3: #REF!
Name cost_pbVAS3: #REF!
Name cost_pbVAS3: #REF!
Name CUR: '[4]data - main'!$AH$5:$AH$6
Name Currency: '[4]main menu'!$H$4
Name currency_selected: '[6]main menu'!$H$4
Name Currency2: '[4]main menu'!$H$4
Name customer_name: '[4]quote - main'!$C$12
Name data: '[4]quote - data table pricing'!$A$5:$P$1531
Name data_table_pricing: '[4]quote - data table pricing'!$A$4:$P$1531
Name DID_avail: '[4]data - main'!$AX$4:$AY$23
Name DID_CT_DA_ZONE_FIND: VLOOKUP('[4]quote - site BT services'!$D1,'[4]data - PB avail'!$E$5:$U$253,16,FALSE)
Name DID_CT_IP_ZONE_FIND: VLOOKUP('[4]quote - site BT services'!$D1,'[4]data - PB avail'!$E$5:$U$253,15,FALSE)
Name DID_CT_SA_ZONE_FIND: VLOOKUP('[4]quote - site BT services'!$D1,'[4]data - PB avail'!$E$5:$U$253,17,FALSE)
Name DID_DA_1_to_9: IF(DID_CT_DA_ZONE_FIND="DIDZ1",DID_MRP_Z1_VLOOKUP_10,IF(DID_CT_DA_ZONE_FIND="DIDZ2",DID_MRP_Z2_VLOOKUP_10,IF(DID_CT_DA_ZONE_FIND="DIDZ3",DID_MRP_Z3_VLOOKUP_10,DID_CT_DA_ZONE_FIND)))
Name DID_DA_10_to_99: IF(DID_CT_DA_ZONE_FIND="DIDZ1",DID_MRP_Z1_VLOOKUP_100,IF(DID_CT_DA_ZONE_FIND="DIDZ2",DID_MRP_Z2_VLOOKUP_100,IF(DID_CT_DA_ZONE_FIND="DIDZ3",DID_MRP_Z3_VLOOKUP_100,DID_CT_DA_ZONE_FIND)))
Name DID_DA_100_to_999: IF(DID_CT_DA_ZONE_FIND="DIDZ1",DID_MRP_Z1_VLOOKUP_1000,IF(DID_CT_DA_ZONE_FIND="DIDZ2",DID_MRP_Z2_VLOOKUP_1000,IF(DID_CT_DA_ZONE_FIND="DIDZ3",DID_MRP_Z3_VLOOKUP_1000,DID_CT_DA_ZONE_FIND)))
Name DID_DA_1000: IF(DID_CT_DA_ZONE_FIND="DIDZ1",DID_MRP_Z1_VLOOKUP_10000,IF(DID_CT_DA_ZONE_FIND="DIDZ2",DID_MRP_Z2_VLOOKUP_10000,IF(DID_CT_DA_ZONE_FIND="DIDZ3",DID_MRP_Z3_VLOOKUP_10000,DID_CT_DA_ZONE_FIND)))
Name DID_MRP_OUTPUT_1_to_9: IF('[4]quote - site BT services'!XEW1="Dedicated Access",DID_DA_1_to_9,IF('[4]quote - site BT services'!XEW1="Switched Access",DID_SA_1_to_9,DID_IP_1_to_9))
Name DID_MRP_OUTPUT_10_to_99: IF('[4]quote - site BT services'!XEW1="Dedicated Access",DID_DA_10_to_99,IF('[4]quote - site BT services'!XEW1="Switched Access",DID_SA_10_to_99,DID_IP_10_to_99))
Name DID_MRP_OUTPUT_100_to_999: IF('[4]quote - site BT services'!XEW1="Dedicated Access",DID_DA_100_to_999,IF('[4]quote - site BT services'!XEW1="Switched Access",DID_SA_100_to_999,DID_IP_100_to_999))
Name DID_MRP_OUTPUT_1000: IF('[4]quote - site BT services'!XEW1="Dedicated Access",DID_DA_1000,IF('[4]quote - site BT services'!XEW1="Switched Access",DID_SA_1000,DID_IP_1000))
Name DID_MRP_Z1_VLOOKUP_10: (VLOOKUP("DID Z1 10",'[4]data - Portal PB other'!$B$8:$S$26,18,FALSE)*active_forex)
Name DID_MRP_Z1_VLOOKUP_100: (VLOOKUP("DID Z1 100",'[4]data - Portal PB other'!$B$8:$S$26,18,FALSE)*active_forex)

Sheet Main Menu
D1: Voice Price Book
D2: SITA Voice Price Book Year 21 - v1.0
B7: =INDEX(MenuItems,'[8]Main menu'!$A$7,0) -> #NAME? | D7: PBy20 STANDARD PRICE BOOK
P10: Access
D11: Contact Center
D12: (All CC Services follow VACS1 Program except IN and NCM) | Q12: >> PSTN Termination
E14: >> PSTN call collection
E16: >> Toll Free call collection
P17: Reference Information
E18: >> UIFN call collection
Q19: >> Country & destination codes
E20: >> Toll Share surcharges
E24: >> Network Contact Manager (NCM)

Sheet PSTN Termination
B1: >> Main Menu
B3: PSTN Termination (Contact Center)
B4: PILOT VACS1 Schedule
B7: All rates in USD
B8: All prices exclude VAT and apply at all times of day.
F11: PSTN Termination
B12: Code | C12: Collecting Country | D12: ISO Code | E12: Termination | F12: Per minute
B13: SURPSTN AFG | C13: Afghanistan | D13: AFG | F13: 0.1578
B14: SURPSTN AFG MOB | C14: Afghanistan | D14: AFG | E14: MOB | F14: 0.1578
B15: SURPSTN ALB | C15: Albania | D15: ALB | F15: 0.164
B16: SURPSTN ALB MOB | C16: Albania | D16: ALB | E16: MOB | F16: 0.4305
B17: SURPSTN DZA | C17: Algeria | D17: DZA | F17: 0.0625
B18: SURPSTN DZA MOB | C18: Algeria | D18: DZA | E18: MOB | F18: 0.7026
B19: SURPSTN ASM | C19: American Samoa | D19: ASM | F19: 1.3021
B20: SURPSTN ASM MOB | C20: American Samoa | D20: ASM | E20: MOB | F20: 1.3021
B21: SURPSTN AND | C21: Andorra | D21: AND | F21: 0.0203
B22: SURPSTN AND MOB | C22: Andorra | D22: AND | E22: MOB | F22: 0.137
B23: SURPSTN AGO | C23: Angola | D23: AGO | F23: 0.0497
B24: SURPSTN AGO MOB | C24: Angola | D24: AGO | E24: MOB | F24: 0.1977
B25: SURPSTN AIA | C25: Anguilla | D25: AIA | F25: 0.2545
B26: SURPSTN AIA MOB | C26: Anguilla | D26: AIA | E26: MOB | F26: 0.2545
B27: SURPSTN ATA | C27: Antarctica | D27: ATA | F27: 1.4002
B28: SURPSTN ATA MOB | C28: Antarctica | D28: ATA | E28: MOB | F28: 1.4002
B29: SURPSTN ATG | C29: Antigua & Barbuda | D29: ATG | F29: 0.3004
B30: SURPSTN ATG MOB | C30: Antigua & Barbuda | D30: ATG | E30: MOB | F30: 0.3004
B31: SURPSTN ARG | C31: Argentina | D31: ARG | F31: 0.0124
B32: SURPSTN ARG MOB | C32: Argentina | D32: ARG | E32: MOB | F32: 0.1799
B33: SURPSTN ARM | C33: Armenia | D33: ARM | F33: 0.2165
B34: SURPSTN ARM MOB | C34: Armenia | D34: ARM | E34: MOB | F34: 0.2354
B35: SURPSTN ABW | C35: Aruba | D35: ABW | F35: 0.1104
B36: SURPSTN ABW MOB | C36: Aruba | D36: ABW | E36: MOB | F36: 0.2285
B37: SURPSTN AUS | C37: Australia | D37: AUS | F37: 0.0117
B38: SURPSTN AUS MOB | C38: Australia | D38: AUS | E38: MOB | F38: 0.0403
B39: SURPSTN AUT | C39: Austria | D39: AUT | F39: 0.0057
B40: SURPSTN AUT MOB | C40: Austria | D40: AUT | E40: MOB | F40: 0.0165
B41: SURPSTN AZE | C41: Azerbaijan | D41: AZE | F41: 0.2012
B42: SURPSTN AZE MOB | C42: Azerbaijan | D42: AZE | E42: MOB | F42: 0.3243
B43: SURPSTN BHS | C43: Bahamas | D43: BHS | F43: 0.2542
B44: SURPSTN BHS MOB | C44: Bahamas | D44: BHS | E44: MOB | F44: 0.2542
B45: SURPSTN BHR | C45: Bahrain | D45: BHR | F45: 0.1285
B46: SURPSTN BHR MOB | C46: Bahrain | D46: BHR | E46: MOB | F46: 0.1285
B47: SURPSTN BGD | C47: Bangladesh | D47: BGD | F47: 0.0395
B48: SURPSTN BGD MOB | C48: Bangladesh | D48: BGD | E48: MOB | F48: 0.0333
B49: SURPSTN BRB | C49: Barbados | D49: BRB | F49: 0.2532
B50: SURPSTN BRB MOB | C50: Barbados | D50: BRB | E50: MOB | F50: 0.2532
B51: SURPSTN BLR | C51: Belarus | D51: BLR | F51: 0.3746
B52: SURPSTN BLR MOB | C52: Belarus | D52: BLR | E52: MOB | F52: 0.3679
B53: SURPSTN BEL | C53: Belgium | D53: BEL | F53: 0.0108
B54: SURPSTN BEL MOB | C54: Belgium | D54: BEL | E54: MOB | F54: 0.0161
B55: SURPSTN BLZ | C55: Belize | D55: BLZ | F55: 0.234
B56: SURPSTN BLZ MOB | C56: Belize | D56: BLZ | E56: MOB | F56: 0.2338
B57: SURPSTN BEN | C57: Benin | D57: BEN | F57: 0.2542
B58: SURPSTN BEN MOB | C58: Benin | D58: BEN | E58: MOB | F58: 0.335
B59: SURPSTN BMU | C59: Bermuda | D59: BMU | F59: 0.0562
B60: SURPSTN BMU MOB | C60: Bermuda | D60: BMU | E60: MOB | F60: 0.0562
B61: SURPSTN BTN | C61: Bhutan | D61: BTN | F61: 0.0633
B62: SURPSTN BTN MOB | C62: Bhutan | D62: BTN | E62: MOB | F62: 0.0633
B63: SURPSTN BOL | C63: Bolivia | D63: BOL | F63: 0.119
B64: SURPSTN BOL MOB | C64: Bolivia | D64: BOL | E64: MOB | F64: 0.2144
B65: SURPSTN BES | C65: Bonaire | D65: BES | F65: 0.1629
B66: SURPSTN BES MOB | C66: Bonaire | D66: BES | E66: MOB | F66: 0.198
B67: SURPSTN BIH | C67: Bosnia/Herzegovina | D67: BIH | F67: 0.1554
B68: SURPSTN BIH MOB | C68: Bosnia/Herzegovina | D68: BIH | E68: MOB | F68: 0.3984
B69: SURPSTN BWA | C69: Botswana | D69: BWA | F69: 0.184
B70: SURPSTN BWA MOB | C70: Botswana | D70: BWA | E70: MOB | F70: 0.2664
B71: SURPSTN BRA | C71: Brazil | D71: BRA | F71: 0.005
B72: SURPSTN BRA MOB | C72: Brazil | D72: BRA | E72: MOB | F72: 0.0118
B73: SURPSTN BRN | C73: Brunei | D73: BRN | F73: 0.0365
B74: SURPSTN BRN MOB | C74: Brunei | D74: BRN | E74: MOB | F74: 0.0332
B75: SURPSTN BGR | C75: Bulgaria | D75: BGR | F75: 0.0225
B76: SURPSTN BGR MOB | C76: Bulgaria | D76: BGR | E76: MOB | F76: 0.0256
B77: SURPSTN BFA | C77: Burkina | D77: BFA | F77: 0.3916
B78: SURPSTN BFA MOB | C78: Burkina | D78: BFA | E78: MOB | F78: 0.3914
B79: SURPSTN BDI | C79: Burundi | D79: BDI | F79: 0.6058
B80: SURPSTN BDI MOB | C80: Burundi | D80: BDI | E80: MOB | F80: 0.6195
B81: SURPSTN KHM | C81: Cambodia | D81: KHM | F81: 0.0764
B82: SURPSTN KHM MOB | C82: Cambodia | D82: KHM | E82: MOB | F82: 0.0752
B83: SURPSTN CMR | C83: Cameroon | D83: CMR | F83: 0.128
B84: SURPSTN CMR MOB | C84: Cameroon | D84: CMR | E84: MOB | F84: 0.3647
B85: SURPSTN CAN | C85: Canada | D85: CAN | F85: 0.0071
B86: SURPSTN CAN MOB | C86: Canada | D86: CAN | E86: MOB | F86: 0.0071
B87: SURPSTN CPV | C87: Cape Verde | D87: CPV | F87: 0.2623
B88: SURPSTN CPV MOB | C88: Cape Verde | D88: CPV | E88: MOB | F88: 0.2623
B89: SURPSTN CYM | C89: Cayman Isl | D89: CYM | F89: 0.1695
B90: SURPSTN CYM MOB | C90: Cayman Isl | D90: CYM | E90: MOB | F90: 0.166
B91: SURPSTN CAF | C91: Central African Rep | D91: CAF | F91: 0.2976
B92: SURPSTN CAF MOB | C92: Central African Rep | D92: CAF | E92: MOB | F92: 0.5993
B93: SURPSTN TCD | C93: Chad | D93: TCD | F93: 0.5592
B94: SURPSTN TCD MOB | C94: Chad | D94: TCD | E94: MOB | F94: 0.5592
B95: SURPSTN CHL | C95: Chile | D95: CHL | F95: 0.0129
B96: SURPSTN CHL MOB | C96: Chile | D96: CHL | E96: MOB | F96: 0.0276
B97: SURPSTN CHN | C97: China | D97: CHN | F97: 0.022
B98: SURPSTN CHN MOB | C98: China | D98: CHN | E98: MOB | F98: 0.0246
B99: SURPSTN COL | C99: Colombia | D99: COL | F99: 0.02
B100: SURPSTN COL MOB | C100: Colombia | D100: COL | E100: MOB | F100: 0.0186
B101: SURPSTN COM | C101: Comoros | D101: COM | F101: 0.5601
B102: SURPSTN COM MOB | C102: Comoros | D102: COM | E102: MOB | F102: 0.5342
B103: SURPSTN COG | C103: Congo | D103: COG | F103: 0.4061
B104: SURPSTN COG MOB | C104: Congo | D104: COG | E104: MOB | F104: 0.4435
B105: SURPSTN COK | C105: Cook Isl | D105: COK | F105: 1.8595
...

Sheet PSTN
B1: >> Main Menu | S1: =_xlfn.TEXTJOIN(",",,R1:R4)
B3: Contact Center - PSTN Call Collection Prices
B4: PILOT VACS1 Schedule
B7: All rates in USD
B8: All prices exclude VAT and apply at all times of day.
B9: 'na' indicates not available as a standard service, please see Voice Availaibility Matrix.
B10: TPM charges not applicable to Advance PSTN Call Usage
G15: Fixed Charges Per Number
F16: PSTN Call Usage | G16: Code | H16: Installation | I16: Rental
A17: unique ID | B17: Code Usage | C17: Collecting Country | D17: ISO Code | E17: Origination | F17: Per minute | G17: Per Number | H17: One time | I17: Monthly
A18: PSTN ALB | B18: PSTN ALB | C18: Albania | D18: ALB | F18: 0.0273 | G18: PSTNNUM ALB | H18: 89.6 | I18: 13.44
A19: PSTN DZA | B19: PSTN ALB MOB | C19: Albania | D19: ALB | E19: MOB | F19: 0.0273
A20: PSTN AGO | B20: PSTN DZA | C20: Algeria | D20: DZA | F20: 0.0728 | G20: PSTNNUM DZA | H20: 93.57 | I20: 14.875
A21: PSTN ARG | B21: PSTN DZA MOB | C21: Algeria | D21: DZA | E21: MOB | F21: 0.0728
A22: PSTN AUS | B22: PSTN AGO | C22: Angola | D22: =VLOOKUP(C22,'Country & dest. codes'!$B$7:$F$250,5,0) -> AGO | F22: 0.0363 | G22: PSTNNUM AGO | H22: 89.6 | I22: 44.8
A23: PSTN AUT | B23: PSTN AGO MOB | C23: Angola | D23: =VLOOKUP(C23,'Country & dest. codes'!$B$7:$F$250,5,0) -> AGO | E23: MOB | F23: 0.0363
A24: PSTN BGD | B24: PSTN ARG | C24: Argentina | D24: ARG | F24: 0.0095 | G24: PSTNNUM ARG | H24: 93.57 | I24: 12.21
A25: PSTN BLR | B25: PSTN ARG MOB | C25: Argentina | D25: ARG | E25: MOB | F25: 0.0095
A26: PSTN BEL | B26: PSTN AUS | C26: Australia | D26: AUS | F26: 0.006 | G26: PSTNNUM AUS | H26: 93.57 | I26: 12.21
A27: PSTN BEN | B27: PSTN AUS MOB | C27: Australia | D27: AUS | E27: MOB | F27: 0.006
A28: PSTN BIH | B28: PSTN AUT | C28: Austria | D28: AUT | F28: 0.006 | G28: PSTNNUM AUT | H28: 93.57 | I28: 4.07
A29: PSTN BRA | B29: PSTN AUT MOB | C29: Austria | D29: AUT | E29: MOB | F29: 0.006
A30: PSTN BGR | B30: PSTN BGD | C30: Bangladesh | D30: BGD | F30: 0.1067 | G30: PSTNNUM BGD | H30: 93.57 | I30: 33.6
A31: PSTN BFA | B31: PSTN BGD MOB | C31: Bangladesh | D31: BGD | E31: MOB | F31: 0.1067
A32: PSTN KHM | B32: PSTN BLR | C32: Belarus | D32: =VLOOKUP(C32,'Country & dest. codes'!$B$7:$F$250,5,0) -> BLR | F32: 0.0343 | G32: PSTNNUM BLR | H32: 134.4 | I32: 89.6
A33: PSTN CMR | B33: PSTN BLR MOB | C33: Belarus | D33: =VLOOKUP(C33,'Country & dest. codes'!$B$7:$F$250,5,0) -> BLR | E33: MOB | F33: 0.0343
A34: PSTN CAN | B34: PSTN BEL | C34: Belgium | D34: BEL | F34: 0.006 | G34: PSTNNUM BEL | H34: 93.57 | I34: 0.68
A35: PSTN CYM | B35: PSTN BEL MOB | C35: Belgium | D35: BEL | E35: MOB | F35: 0.006
A36: PSTN CHL | B36: PSTN BEN | C36: Benin | D36: BEN | F36: 0.2429 | G36: PSTNNUM BEN | H36: 93.57 | I36: 89.6
A37: PSTN CHN | B37: PSTN BEN MOB | C37: Benin | D37: BEN | E37: MOB | F37: 0.2429
A38: PSTN COL | B38: PSTN BIH | C38: Bosnia | D38: BIH | F38: 0.0269 | G38: PSTNNUM BIH | H38: 89.6 | I38: 19.2
A39: PSTN CRI | B39: PSTN BIH MOB | C39: Bosnia | D39: BIH | E39: MOB | F39: 0.0269
A40: PSTN HRV | B40: PSTN BRA | C40: Brazil | D40: BRA | F40: 0.0095 | G40: PSTNNUM BRA | H40: 93.57 | I40: 12.21
A41: PSTN CYP | B41: PSTN BRA MOB | C41: Brazil | D41: BRA | E41: MOB | F41: 0.0095
A42: PSTN CZE | B42: PSTN BGR | C42: Bulgaria | D42: BGR | F42: 0.0095 | G42: PSTNNUM BGR | H42: 93.57 | I42: 12.21
A43: PSTN DNK | B43: PSTN BGR MOB | C43: Bulgaria | D43: BGR | E43: MOB | F43: 0.0095
A44: PSTN DOM | B44: PSTN BFA | C44: Burkina Faso | D44: BFA | F44: 0.3614 | G44: PSTNNUM BFA | H44: 134.4 | I44: 89.25
A45: PSTN SLV | B45: PSTN BFA MOB | C45: Burkina Faso | D45: BFA | E45: MOB | F45: 0.3614
A46: PSTN EST | B46: PSTN KHM | C46: Cambodia | D46: KHM | F46: 0.2861 | G46: PSTNNUM KHM | H46: 179.2 | I46: 89.6
A47: PSTN FIN | B47: PSTN KHM MOB | C47: Cambodia | D47: KHM | E47: MOB | F47: 0.2861
A48: PSTN FRA | B48: PSTN CMR | C48: Cameroon | D48: CMR | F48: 0.2821 | G48: PSTNNUM CMR | H48: 128 | I48: 44.8
A49: PSTN GUF | B49: PSTN CMR MOB | C49: Cameroon | D49: CMR | E49: MOB | F49: 0.2821
A50: PSTN GEO | B50: PSTN CAN | C50: Canada | D50: CAN | F50: 0.006 | G50: PSTNNUM CAN | H50: 93.57 | I50: 12.21
A51: PSTN DEU | B51: PSTN CAN MOB | C51: Canada | D51: CAN | E51: MOB | F51: 0.006
A52: PSTN GHA | B52: PSTN CYM | C52: Cayman Islands | D52: CYM | F52: 0.018 | G52: PSTNNUM CYM | H52: 89.6 | I52: 89.6
A53: PSTN GRC | B53: PSTN CYM MOB | C53: Cayman Islands | D53: CYM | E53: MOB | F53: 0.018
A54: PSTN GRD | B54: PSTN CHL | C54: Chile | D54: CHL | F54: 0.0095 | G54: PSTNNUM CHL | H54: 93.57 | I54: 12.21
A55: PSTN GLP | B55: PSTN CHL MOB | C55: Chile | D55: CHL | E55: MOB | F55: 0.0095
A56: PSTN GTM | B56: PSTN CHN | C56: China | D56: CHN | F56: 0.034 | G56: PSTNNUM CHN | H56: 93.57 | I56: 12.21
A57: PSTN HND | B57: PSTN CHN MOB | C57: China | D57: CHN | E57: MOB | F57: 0.034
A58: PSTN HKG | B58: PSTN COL | C58: Colombia | D58: COL | F58: 0.006 | G58: PSTNNUM COL | H58: 93.57 | I58: 22.4
A59: PSTN HUN | B59: PSTN COL MOB | C59: Colombia | D59: COL | E59: MOB | F59: 0.006
A60: PSTN ISL | B60: PSTN CRI | C60: Costa Rica | D60: CRI | F60: 0.0179 | G60: PSTNNUM CRI | H60: 89.6 | I60: 17.85
A61: PSTN IND | B61: PSTN CRI MOB | C61: Costa Rica | D61: CRI | E61: MOB | F61: 0.0179
A62: PSTN IDN | B62: PSTN HRV | C62: Croatia | D62: HRV | F62: 0.0095 | G62: PSTNNUM HRV | H62: 93.57 | I62: 12.21
A63: PSTN IRL | B63: PSTN HRV MOB | C63: Croatia | D63: HRV | E63: MOB | F63: 0.0095
A64: PSTN ISR | B64: PSTN CYP | C64: Cyprus | D64: CYP | F64: 0.0123 | G64: PSTNNUM CYP | H64: 93.57 | I64: 12.21
A65: PSTN ITA | B65: PSTN CYP MOB | C65: Cyprus | D65: CYP | E65: MOB | F65: 0.0123
A66: PSTN CIV | B66: PSTN CZE | C66: Czech Republic | D66: CZE | F66: 0.006 | G66: PSTNNUM CZE | H66: 93.57 | I66: 12.21
A67: PSTN JAM | B67: PSTN CZE MOB | C67: Czech Republic | D67: CZE | E67: MOB | F67: 0.006
A68: PSTN JPN | B68: PSTN DNK | C68: Denmark | D68: DNK | F68: 0.006 | G68: PSTNNUM DNK | H68: 93.57 | I68: 4.07
A69: PSTN JOR | B69: PSTN DNK MOB | C69: Denmark | D69: DNK | E69: MOB | F69: 0.006
A70: PSTN KAZ | B70: PSTN DOM | C70: Dominican Republic | D70: DOM | F70: 0.0095 | G70: PSTNNUM DOM | H70: 93.57 | I70: 12.21
A71: PSTN KEN | B71: PSTN DOM MOB | C71: Dominican Republic | D71: DOM | E71: MOB | F71: 0.0095
A72: PSTN XKX | B72: PSTN SLV | C72: El Salvador | D72: SLV | F72: 0.0095 | G72: PSTNNUM SLV | H72: 93.57 | I72: 12.21
A73: PSTN KWT | B73: PSTN SLV MOB | C73: El Salvador | D73: SLV | E73: MOB | F73: 0.0095
A74: PSTN KGZ | B74: PSTN EST | C74: Estonia | D74: EST | F74: 0.012 | G74: PSTNNUM EST | H74: 93.57 | I74: 12.21
A75: PSTN LVA | B75: PSTN EST MOB | C75: Estonia | D75: EST | E75: MOB | F75: 0.012
A76: PSTN LTU | B76: PSTN FIN | C76: Finland | D76: FIN | F76: 0.006 | G76: PSTNNUM FIN | H76: 93.57 | I76: 12.21
A77: PSTN LUX | B77: PSTN FIN MOB | C77: Finland | D77: FIN | E77: MOB | F77: 0.006
A78: PSTN MAC | B78: PSTN FRA | C78: France | D78: FRA | F78: 0.006 | G78: PSTNNUM FRA | H78: 93.57 | I78: 0.68
A79: PSTN MKD | B79: PSTN FRA MOB | C79: France | D79: FRA | E79: MOB | F79: 0.006
A80: PSTN MYS | B80: PSTN GUF | C80: French Guiana | D80: GUF | F80: 0.064 | G80: PSTNNUM GUF | H80: 93.57 | I80: 12.21
A81: PSTN MLT | B81: PSTN GUF MOB | C81: French Guiana | D81: GUF | E81: MOB | F81: 0.064
A82: PSTN MTQ | B82: PSTN GEO | C82: Georgia | D82: GEO | F82: 0.0123 | G82: PSTNNUM GEO | H82: 89.6 | I82: 19.2
A83: PSTN MUS | B83: PSTN GEO MOB | C83: Georgia | D83: GEO | E83: MOB | F83: 0.0123
A84: PSTN MEX | B84: PSTN DEU | C84: Germany | D84: DEU | F84: 0.006 | G84: PSTNNUM DEU | H84: 93.57 | I84: 4.07
A85: PSTN MDA | B85: PSTN DEU MOB | C85: Germany | D85: DEU | E85: MOB | F85: 0.006
A86: PSTN MNE | B86: PSTN GHA | C86: Ghana | D86: GHA | F86: 0.0938 | G86: PSTNNUM GHA | H86: 89.6 | I86: 44.8
A87: PSTN MAR | B87: PSTN GHA MOB | C87: Ghana | D87: GHA | E87: MOB | F87: 0.0938
A88: PSTN NLD | B88: PSTN GRC | C88: Greece | D88: GRC | F88: 0.0095 | G88: PSTNNUM GRC | H88: 93.57 | I88: 12.21
A89: PSTN NZL | B89: PSTN GRC MOB | C89: Greece | D89: GRC | E89: MOB | F89: 0.0095
A90: PSTN NIC | B90: PSTN GRD | C90: Grenada | D90: =VLOOKUP(C90,'Country & dest. codes'!$B$7:$F$250,5,0) -> GRD | F90: 0.0257 | G90: PSTNNUM GRD | H90: 89.6 | I90: 89.6
A91: PSTN NGA | B91: PSTN GRD MOB | C91: Grenada | D91: =VLOOKUP(C91,'Country & dest. codes'!$B$7:$F$250,5,0) -> GRD | E91: MOB | F91: 0.0257
A92: PSTN NOR | B92: PSTN GLP | C92: Guadaloupe | D92: GLP | F92: 0.064 | G92: PSTNNUM GLP | H92: 89.6 | I92: 26.88
A93: PSTN PAK | B93: PSTN GLP MOB | C93: Guadaloupe | D93: GLP | E93: MOB | F93: 0.064
A94: PSTN PAN | B94: PSTN GTM | C94: Guatemala | D94: GTM | F94: 0.4472 | G94: PSTNNUM GTM | H94: 128 | I94: 89.6
A95: PSTN PER | B95: PSTN GTM MOB | C95: Guatemala | D95: GTM | E95: MOB | F95: 0.4472
A96: PSTN PHL | B96: PSTN HND | C96: Honduras | D96: HND | F96: 0.1289 | G96: PSTNNUM HND | H96: 179.2 | I96: 47.6
A97: PSTN POL | B97: PSTN HND MOB | C97: Honduras | D97: HND | E97: MOB | F97: 0.1289
A98: PSTN PRT | B98: PSTN HKG | C98: Hong Kong | D98: HKG | F98: 0.0139 | G98: PSTNNUM HKG | H98: 93.57 | I98: 0.68
A99: PSTN PRI | B99: PSTN HKG MOB | C99: Hong Kong | D99: HKG | E99: MOB | F99: 0.0139
B100: PSTN HUN | C100: Hungary | D100: HUN | F100: 0.0095 | G100: PSTNNUM HUN | H100: 93.57 | I100: 12.21
A101: PSTN ROU | B101: PSTN HUN MOB | C101: Hungary | D101: HUN | E101: MOB | F101: 0.0095
A102: PSTN RUS | B102: PSTN ISL | C102: Iceland | D102: =VLOOKUP(C102,'Country & dest. codes'!$B$7:$F$250,5,0) -> ISL | F102: 0.0343 | G102: PSTNNUM ISL | H102: 89.6 | I102: 89.6
A103: PSTN SAU | B103: PSTN ISL MOB | C103: Iceland | D103: =VLOOKUP(C103,'Country & dest. codes'!$B$7:$F$250,5,0) -> ISL | E103: MOB | F103: 0.0343
A104: PSTN SRB | B104: PSTN IND | C104: India | D104: =VLOOKUP(C104,'Country & dest. codes'!$B$7:$F$250,5,0) -> IND | F104: 0.057 | G104: PSTNNUM IND | H104: 179.2 | I104: 89.6
A105: PSTN SYC | B105: PSTN IND MOB | C105: India | D105: =VLOOKUP(C105,'Country & dest. codes'!$B$7:$F$250,5,0) -> IND | E105: MOB | F105: 0.057
A106: PSTN SGP | B106: PSTN IDN | C106: Indonesia | D106: IDN | F106: 0.0595 | G106: PSTNNUM IDN | H106: 89.6 | I106: 19.2
A107: PSTN SVK | B107: PSTN IDN MOB | C107: Indonesia | D107: IDN | E107: MOB | F107: 0.0595
...

Sheet Toll Free
B1: >> Main Menu
B3: Contact Center - Toll Free Call Collection Prices
B4: PILOT VACS1 Schedule
B7: All rates in USD
B8: All prices exclude VAT and apply at all times of day.
B9: 'na' indicates not available as a standard service, please see Voice Availaibility Matrix.
B10: TPM charges not applicable to Advance Toll Free Call Usage
G14: Fixed Charges Per Number
F15: Toll Free Call Usage | G15: Code | H15: Installation | I15: Rental
B16: Code Usage | C16: Collecting Country | D16: ISO Code | E16: Origination | F16: Per minute | G16: Per Number | H16: One time | I16: Monthly
B17: TF ARG | C17: Argentina | D17: ARG | F17: 0.0476 | G17: =IF(H17="","","TFNUM"&" "&D17) -> TFNUM ARG | H17: 168.43 | I17: 12.2135
B18: TF ARG MOB | C18: Argentina | D18: ARG | E18: MOB | F18: 0.0476
B19: TF AUS | C19: Australia | D19: AUS | F19: 0.0134 | G19: =IF(H19="","","TFNUM"&" "&D19) -> TFNUM AUS | H19: 168.43 | I19: 16.2815
B20: TF AUS MOB | C20: Australia | D20: AUS | E20: MOB | F20: 0.022
B21: TF AUT | C21: Austria | D21: AUT | F21: 0.0415 | G21: =IF(H21="","","TFNUM"&" "&D21) -> TFNUM AUT | H21: 168.43 | I21: 12.2135
B22: TF AUT MOB | C22: Austria | D22: AUT | E22: MOB | F22: 0.1338
B23: TF BHS | C23: Bahamas | D23: BHS | F23: 0.1227 | G23: =IF(H23="","","TFNUM"&" "&D23) -> TFNUM BHS | H23: 206.64 | I23: 28.495
B24: TF BHS MOB | C24: Bahamas | D24: BHS | E24: MOB | F24: 0.1227
B25: TF BLR | C25: Belarus | D25: BLR | F25: 0.4104 | G25: =IF(H25="","","TFNUM"&" "&D25) -> TFNUM BLR | H25: 168.43 | I25: 28.495
B26: TF BLR MOB | C26: Belarus | D26: BLR | E26: MOB | F26: 0.4104
B27: TF BEL | C27: Belgium | D27: BEL | F27: 0.0207 | G27: =IF(H27="","","TFNUM"&" "&D27) -> TFNUM BEL | H27: 168.43 | I27: 12.2135
B28: TF BEL MOB | C28: Belgium | D28: BEL | E28: MOB | F28: 0.2149
B29: TF BLZ | C29: Belize | D29: BLZ | F29: 0.2708 | G29: =IF(H29="","","TFNUM"&" "&D29) -> TFNUM BLZ | H29: 168.43 | I29: 28.5
B30: TF BLZ MOB | C30: Belize | D30: BLZ | E30: MOB | F30: 0.2708
B31: TF BMU | C31: Bermuda | D31: BMU | F31: 0.0843 | G31: =IF(H31="","","TFNUM"&" "&D31) -> TFNUM BMU | H31: 168.43 | I31: 28.5
B32: TF BMU MOB | C32: Bermuda | D32: BMU | E32: MOB | F32: 0.0843
B33: TF BWA | C33: Botswana | D33: BWA | F33: 0.5022 | G33: =IF(H33="","","TFNUM"&" "&D33) -> TFNUM BWA | H33: 100.8 | I33: 28.495
B34: TF BWA MOB | C34: Botswana | D34: BWA | E34: MOB | F34: 0.5022
B35: TF BRA | C35: Brazil | D35: BRA | F35: 0.0124 | G35: =IF(H35="","","TFNUM"&" "&D35) -> TFNUM BRA | H35: 440.8375 | I35: 67.2
B36: TF BRA MOB | C36: Brazil | D36: BRA | E36: MOB | F36: 0.0477
B37: TF BRN | C37: Brunei | D37: BRN | F37: 0.2708 | G37: =IF(H37="","","TFNUM"&" "&D37) -> TFNUM BRN | H37: 168.43 | I37: 28.495
B38: TF BRN MOB | C38: Brunei | D38: BRN | E38: MOB | F38: 0.2708
B39: TF BGR | C39: Bulgaria | D39: BGR | F39: 0.0414 | G39: =IF(H39="","","TFNUM"&" "&D39) -> TFNUM BGR | H39: 168.43 | I39: 28.495
B40: TF BGR MOB | C40: Bulgaria | D40: BGR | E40: MOB | F40: 0.1559
B41: TF KHM | C41: Cambodia | D41: =VLOOKUP(C41,PSTN!C:D,2,0) -> KHM | F41: 0.4041 | G41: =IF(H41="","","TFNUM"&" "&D41) -> TFNUM KHM | H41: 134.4 | I41: 134.4
B42: TF KHM MOB | C42: Cambodia | D42: =VLOOKUP(C42,PSTN!C:D,2,0) -> KHM | E42: MOB | F42: 0.4041
B43: TF CAN | C43: Canada | D43: CAN | F43: 0.0083 | G43: =IF(H43="","","TFNUM"&" "&D43) -> TFNUM CAN | H43: 168.43 | I43: 12.2135
B44: TF CAN MOB | C44: Canada | D44: CAN | E44: MOB | F44: 0.0083
B45: TF CHL | C45: Chile | D45: CHL | F45: 0.0313 | G45: =IF(H45="","","TFNUM"&" "&D45) -> TFNUM CHL | H45: 168.43 | I45: 26.88
B46: TF CHL MOB | C46: Chile | D46: CHL | E46: MOB | F46: 0.0313
B47: TF CHN | C47: China | D47: CHN | F47: 0.0898 | G47: =IF(H47="","","TFNUM"&" "&D47) -> TFNUM CHN | H47: 168.43 | I47: 28.495
B48: TF CHN MOB | C48: China | D48: CHN | E48: MOB | F48: 0.0898
B49: TF COL | C49: Colombia | D49: COL | F49: 0.106 | G49: =IF(H49="","","TFNUM"&" "&D49) -> TFNUM COL | H49: 168.43 | I49: 12.2135
B50: TF COL MOB | C50: Colombia | D50: COL | E50: MOB | F50: 0.1213
B51: TF CRI | C51: Costa Rica | D51: CRI | F51: 0.2635 | G51: =IF(H51="","","TFNUM"&" "&D51) -> TFNUM CRI | H51: 168.43 | I51: 28.495
B52: TF CRI MOB | C52: Costa Rica | D52: CRI | E52: MOB | F52: 0.2635
B53: TF HRV | C53: Croatia | D53: HRV | F53: 0.0605 | G53: =IF(H53="","","TFNUM"&" "&D53) -> TFNUM HRV | H53: 168.43 | I53: 28.495
B54: TF HRV MOB | C54: Croatia | D54: HRV | E54: MOB | F54: 0.1904
B55: TF CYP | C55: Cyprus | D55: CYP | F55: 0.0344 | G55: =IF(H55="","","TFNUM"&" "&D55) -> TFNUM CYP | H55: 168.43 | I55: 28.5
B56: TF CYP MOB | C56: Cyprus | D56: CYP | E56: MOB | F56: 0.0344
B57: TF CZE | C57: Czech Republic | D57: CZE | F57: 0.0263 | G57: =IF(H57="","","TFNUM"&" "&D57) -> TFNUM CZE | H57: 168.43 | I57: 12.2135
B58: TF CZE MOB | C58: Czech Republic | D58: CZE | E58: MOB | F58: 0.1066
B59: TF DNK | C59: Denmark | D59: DNK | F59: 0.0087 | G59: =IF(H59="","","TFNUM"&" "&D59) -> TFNUM DNK | H59: 168.43 | I59: 28.495
B60: TF DNK MOB | C60: Denmark | D60: DNK | E60: MOB | F60: 0.1875
B61: TF DOM | C61: Dominican Republic | D61: DOM | F61: 0.0706 | G61: =IF(H61="","","TFNUM"&" "&D61) -> TFNUM DOM | H61: 168.43 | I61: 28.495
B62: TF DOM MOB | C62: Dominican Republic | D62: DOM | E62: MOB | F62: 0.0706
B63: TF ECU | C63: Ecuador | D63: ECU | F63: 0.2315 | G63: =IF(H63="","","TFNUM"&" "&D63) -> TFNUM ECU | H63: 168.43 | I63: 134.4
B64: TF ECU MOB | C64: Ecuador | D64: ECU | E64: MOB | F64: 0.2315
B65: TF EGY | C65: Egypt | D65: EGY | F65: 0.3242 | G65: =IF(H65="","","TFNUM"&" "&D65) -> TFNUM EGY | H65: 268.8 | I65: 28.5
B66: TF EGY MOB | C66: Egypt | D66: EGY | E66: MOB | F66: 0.3242
B67: TF EST | C67: Estonia | D67: EST | F67: 0.0221 | G67: =IF(H67="","","TFNUM"&" "&D67) -> TFNUM EST | H67: 168.43 | I67: 28.56
B68: TF EST MOB | C68: Estonia | D68: EST | E68: MOB | F68: 0.4635
B69: TF FIN | C69: Finland | D69: FIN | F69: 0.0491 | G69: =IF(H69="","","TFNUM"&" "&D69) -> TFNUM FIN | H69: 168.43 | I69: 12.2135
B70: TF FIN MOB | C70: Finland | D70: FIN | E70: MOB | F70: 0.0997
B71: TF FRA | C71: France | D71: FRA | F71: 0.0152 | G71: =IF(H71="","","TFNUM"&" "&D71) -> TFNUM FRA | H71: 168.43 | I71: 12.2135
B72: TF FRA MOB | C72: France | D72: FRA | E72: MOB | F72: 0.0543
B73: TF GUF | C73: French Guyana | D73: GUF | F73: 0.1384 | G73: =IF(H73="","","TFNUM"&" "&D73) -> TFNUM GUF | H73: 206.64 | I73: 28.495
B74: TF GUF MOB | C74: French Guyana | D74: GUF | E74: MOB | F74: 0.1384
B75: TF DEU | C75: Germany | D75: DEU | F75: 0.0057 | G75: =IF(H75="","","TFNUM"&" "&D75) -> TFNUM DEU | H75: 168.43 | I75: 12.2135
B76: TF DEU MOB | C76: Germany | D76: DEU | E76: MOB | F76: 0.0793
B77: TF GRC | C77: Greece | D77: GRC | F77: 0.0583 | G77: =IF(H77="","","TFNUM"&" "&D77) -> TFNUM GRC | H77: 168.43 | I77: 12.2135
B78: TF GRC MOB | C78: Greece | D78: GRC | E78: MOB | F78: 0.2741
B79: TF GLP | C79: Guadaloupe | D79: GLP | F79: 0.1384 | G79: =IF(H79="","","TFNUM"&" "&D79) -> TFNUM GLP | H79: 206.64 | I79: 28.495
B80: TF GLP MOB | C80: Guadaloupe | D80: GLP | E80: MOB | F80: 0.1384
B81: TF GUM | C81: Guam | D81: GUM | F81: 0.0618 | G81: =IF(H81="","","TFNUM"&" "&D81) -> TFNUM GUM | H81: 168.43 | I81: 28.495
B82: TF GUM MOB | C82: Guam | D82: GUM | E82: MOB | F82: 0.0618
B83: TF HND | C83: Honduras | D83: HND | F83: 0.2328 | G83: =IF(H83="","","TFNUM"&" "&D83) -> TFNUM HND | H83: 1527.35 | I83: 28.5
B84: TF HND MOB | C84: Honduras | D84: HND | E84: MOB | F84: 0.2328
B85: TF HKG | C85: Hong Kong | D85: HKG | F85: 0.0519 | G85: =IF(H85="","","TFNUM"&" "&D85) -> TFNUM HKG | H85: 206.64 | I85: 16.2815
B86: TF HKG MOB | C86: Hong Kong | D86: HKG | E86: MOB | F86: 0.0519
B87: TF HUN | C87: Hungary | D87: HUN | F87: 0.0353 | G87: =IF(H87="","","TFNUM"&" "&D87) -> TFNUM HUN | H87: 95.2 | I87: 28.495
B88: TF HUN MOB | C88: Hungary | D88: HUN | E88: MOB | F88: 0.0632
B89: TF ISL | C89: Iceland | D89: ISL | F89: 0.0506 | G89: =IF(H89="","","TFNUM"&" "&D89) -> TFNUM ISL | H89: 168.43 | I89: 12.2135
B90: TF ISL MOB | C90: Iceland | D90: ISL | E90: MOB | F90: 0.0506
B91: TF IND | C91: India (Domestic) | D91: IND | F91: 0.0863 | G91: =IF(H91="","","TFNUM"&" "&D91) -> TFNUM IND | H91: 168.43 | I91: 28.495
B92: TF IND MOB | C92: India (Domestic) | D92: IND | E92: MOB | F92: 0.0863
B93: TF IND 000800 | C93: India (International) | D93: IND | F93: 0.1283 | G93: =IF(H93="","","TFNUM"&" "&D93) -> TFNUM IND | H93: 168.43 | I93: 28.495
B94: TF IND 000800 MOB | C94: India (International) | D94: IND | E94: MOB | F94: 0.1283
B95: TF IDN | C95: Indonesia | D95: IDN | F95: 0.2029 | G95: =IF(H95="","","TFNUM"&" "&D95) -> TFNUM IDN | H95: 168.43 | I95: 28.495
B96: TF IDN MOB | C96: Indonesia | D96: IDN | E96: MOB | F96: 0.2036
B97: TF IRL | C97: Ireland | D97: IRL | F97: 0.0253 | G97: =IF(H97="","","TFNUM"&" "&D97) -> TFNUM IRL | H97: 168.43 | I97: 12.2135
B98: TF IRL MOB | C98: Ireland | D98: IRL | E98: MOB | F98: 0.2261
B99: TF ISR | C99: Israel | D99: ISR | F99: 0.0519 | G99: =IF(H99="","","TFNUM"&" "&D99) -> TFNUM ISR | H99: 168.43 | I99: 12.2135
B100: TF ISR MOB | C100: Israel | D100: ISR | E100: MOB | F100: 0.0519
B101: TF ITA | C101: Italy | D101: ITA | F101: 0.0144 | G101: =IF(H101="","","TFNUM"&" "&D101) -> TFNUM ITA | H101: 168.43 | I101: 12.2135
B102: TF ITA MOB | C102: Italy | D102: ITA | E102: MOB | F102: 0.0951
B103: TF JPN | C103: Japan | D103: JPN | F103: 0.0283 | G103: =IF(H103="","","TFNUM"&" "&D103) -> TFNUM JPN | H103: 168.43 | I103: 28.495
B104: TF JPN MOB | C104: Japan | D104: JPN | E104: MOB | F104: 0.0916
B105: TF JOR | C105: Jordan | D105: JOR | F105: 0.1837 | G105: =IF(H105="","","TFNUM"&" "&D105) -> TFNUM JOR | H105: 168.43 | I105: 28.5
B106: TF JOR MOB | C106: Jordan | D106: JOR | E106: MOB | F106: 0.2891
...

Sheet UIFN
B2: >> Main Menu
B4: Contact Center - UIFN Call Collection Prices
B5: PILOT VACS1 Schedule
B8: All rates in USD
B9: All prices exclude VAT and apply at all times of day.
B10: 'na' indicates not available as a standard service, please see Voice Availaibility Matrix.
B11: TPM charges not applicable to Advance UIFN Call Usage
G15: Fixed Charges Per Number
F16: UIFN Call Usage | G16: Code | H16: Installation | I16: Rental
B17: Code Usage | C17: Collecting Country | D17: ISO Code | E17: Origination | F17: Per minute | G17: Per Number | H17: One time | I17: Monthly
A18: UIFN ARG | B18: UIFN ARG | C18: Argentina | D18: ARG | F18: 0.1467 | G18: =IF(H18="","","UIFNNUM"&" "&D18) -> UIFNNUM ARG | H18: 233.94 | I18: 16.28
A19: UIFN ARG MOB | B19: UIFN ARG MOB | C19: Argentina | D19: ARG | E19: MOB | F19: 0.1467 | G19: =IF(H19="","","UIFNNUM"&" "&D19)
A20: UIFN BLR | B20: UIFN BLR | C20: Belarus | D20: BLR | F20: 0.3496 | G20: =IF(H20="","","UIFNNUM"&" "&D20) -> UIFNNUM BLR | H20: 380.8 | I20: 20.35
A21: UIFN BLR MOB | B21: UIFN BLR MOB | C21: Belarus | D21: BLR | E21: MOB | F21: 0.3496 | G21: =IF(H21="","","UIFNNUM"&" "&D21)
A22: UIFN LVA | B22: UIFN LVA | C22: Latvia | D22: LVA | F22: 0.1618 | G22: =IF(H22="","","UIFNNUM"&" "&D22) -> UIFNNUM LVA | H22: 380.8 | I22: 16.28
A23: UIFN LVA MOB | B23: UIFN LVA MOB | C23: Latvia | D23: LVA | E23: MOB | F23: 0.1618 | G23: =IF(H23="","","UIFNNUM"&" "&D23)
A24: UIFN NZL | B24: UIFN NZL | C24: New Zealand | D24: NZL | F24: 0.0602 | G24: =IF(H24="","","UIFNNUM"&" "&D24) -> UIFNNUM NZL | H24: 380.8 | I24: 20.35
A25: UIFN NZL MOB | B25: UIFN NZL MOB | C25: New Zealand | D25: NZL | E25: MOB | F25: 0.3687 | G25: =IF(H25="","","UIFNNUM"&" "&D25)
A26: UIFN BEL | B26: UIFN BEL | C26: Belgium | D26: BEL | F26: 0.0213 | G26: =IF(H26="","","UIFNNUM"&" "&D26) -> UIFNNUM BEL | H26: 233.94 | I26: 16.28
A27: UIFN BEL MOB | B27: UIFN BEL MOB | C27: Belgium | D27: BEL | E27: MOB | F27: 0.2117 | G27: =IF(H27="","","UIFNNUM"&" "&D27)
A28: UIFN BRA | B28: UIFN BRA | C28: Brazil | D28: BRA | F28: 0.1207 | G28: =IF(H28="","","UIFNNUM"&" "&D28) -> UIFNNUM BRA | H28: 233.94 | I28: 24.43
A29: UIFN BRA MOB | B29: UIFN BRA MOB | C29: Brazil | D29: BRA | E29: MOB | F29: 0.3484 | G29: =IF(H29="","","UIFNNUM"&" "&D29)
A30: UIFN BGR | B30: UIFN BGR | C30: Bulgaria | D30: BGR | F30: 0.1473 | G30: =IF(H30="","","UIFNNUM"&" "&D30) -> UIFNNUM BGR | H30: 233.94 | I30: 20.35
A31: UIFN BGR MOB | B31: UIFN BGR MOB | C31: Bulgaria | D31: BGR | E31: MOB | F31: 0.1473 | G31: =IF(H31="","","UIFNNUM"&" "&D31)
A32: UIFN PHL | B32: UIFN PHL | C32: Philippines | D32: PHL | F32: 0.2062 | G32: =IF(H32="","","UIFNNUM"&" "&D32) -> UIFNNUM PHL | H32: 380.8 | I32: 20.35
A33: UIFN PHL MOB | B33: UIFN PHL MOB | C33: Philippines | D33: PHL | E33: MOB | F33: 0.2062 | G33: =IF(H33="","","UIFNNUM"&" "&D33)
A34: UIFN CHN | B34: UIFN CHN | C34: China | D34: CHN | F34: 0.2566 | G34: =IF(H34="","","UIFNNUM"&" "&D34) -> UIFNNUM CHN | H34: 233.94 | I34: 24.43
A35: UIFN CHN MOB | B35: UIFN CHN MOB | C35: China | D35: CHN | E35: MOB | F35: 0.2566 | G35: =IF(H35="","","UIFNNUM"&" "&D35)
A36: UIFN COL | B36: UIFN COL | C36: Colombia | D36: COL | F36: 0.2368 | G36: =IF(H36="","","UIFNNUM"&" "&D36) -> UIFNNUM COL | H36: 233.94 | I36: 16.28
A37: UIFN COL MOB | B37: UIFN COL MOB | C37: Colombia | D37: COL | E37: MOB | F37: 0.2262 | G37: =IF(H37="","","UIFNNUM"&" "&D37)
A38: UIFN HRV | B38: UIFN HRV | C38: Croatia | D38: HRV | F38: 0.2518 | G38: =IF(H38="","","UIFNNUM"&" "&D38) -> UIFNNUM HRV | H38: 233.94 | I38: 20.35
A39: UIFN HRV MOB | B39: UIFN HRV MOB | C39: Croatia | D39: HRV | E39: MOB | F39: 0.2518 | G39: =IF(H39="","","UIFNNUM"&" "&D39)
A40: UIFN CYP | B40: UIFN CYP | C40: Cyprus | D40: CYP | F40: 0.0826 | G40: =IF(H40="","","UIFNNUM"&" "&D40) -> UIFNNUM CYP | H40: 233.94 | I40: 16.28
A41: UIFN CYP MOB | B41: UIFN CYP MOB | C41: Cyprus | D41: CYP | E41: MOB | F41: 0.0826 | G41: =IF(H41="","","UIFNNUM"&" "&D41)
A42: UIFN POL | B42: UIFN POL | C42: Poland | D42: POL | F42: 0.0483 | G42: =IF(H42="","","UIFNNUM"&" "&D42) -> UIFNNUM POL | H42: 95.2 | I42: 16.28
A43: UIFN POL MOB | B43: UIFN POL MOB | C43: Poland | D43: POL | E43: MOB | F43: 0.0483 | G43: =IF(H43="","","UIFNNUM"&" "&D43)
A44: UIFN SVN | B44: UIFN SVN | C44: Slovenia | D44: SVN | F44: 0.1301 | G44: =IF(H44="","","UIFNNUM"&" "&D44) -> UIFNNUM SVN | H44: 380.8 | I44: 24.43
A45: UIFN SVN MOB | B45: UIFN SVN MOB | C45: Slovenia | D45: SVN | E45: MOB | F45: 0.1301 | G45: =IF(H45="","","UIFNNUM"&" "&D45)
A46: UIFN KOR | B46: UIFN KOR | C46: South Korea | D46: KOR | F46: 0.1111 | G46: =IF(H46="","","UIFNNUM"&" "&D46) -> UIFNNUM KOR | H46: 380.8 | I46: 24.43
A47: UIFN KOR MOB | B47: UIFN KOR MOB | C47: South Korea | D47: KOR | E47: MOB | F47: 0.1111 | G47: =IF(H47="","","UIFNNUM"&" "&D47)
A48: UIFN AUS | B48: UIFN AUS | C48: Australia | D48: AUS | F48: 0.0376 | G48: =IF(H48="","","UIFNNUM"&" "&D48) -> UIFNNUM AUS | H48: 233.94 | I48: 30.8
A49: UIFN AUS MOB | B49: UIFN AUS MOB | C49: Australia | D49: AUS | E49: MOB | F49: 0.0384 | G49: =IF(H49="","","UIFNNUM"&" "&D49)
A50: UIFN FRA | B50: UIFN FRA | C50: France | D50: FRA | F50: 0.0277 | G50: =IF(H50="","","UIFNNUM"&" "&D50) -> UIFNNUM FRA | H50: 233.94 | I50: 16.28
A51: UIFN FRA MOB | B51: UIFN FRA MOB | C51: France | D51: FRA | E51: MOB | F51: 0.0807 | G51: =IF(H51="","","UIFNNUM"&" "&D51)
A52: UIFN AUT | B52: UIFN AUT | C52: Austria | D52: AUT | F52: 0.0643 | G52: =IF(H52="","","UIFNNUM"&" "&D52) -> UIFNNUM AUT | H52: 233.94 | I52: 26.88
A53: UIFN AUT MOB | B53: UIFN AUT MOB | C53: Austria | D53: AUT | E53: MOB | F53: 0.2307 | G53: =IF(H53="","","UIFNNUM"&" "&D53)
A54: UIFN GRC | B54: UIFN GRC | C54: Greece | D54: GRC | F54: 0.0509 | G54: =IF(H54="","","UIFNNUM"&" "&D54) -> UIFNNUM GRC | H54: 233.94 | I54: 20.35
A55: UIFN GRC MOB | B55: UIFN GRC MOB | C55: Greece | D55: GRC | E55: MOB | F55: 0.2667 | G55: =IF(H55="","","UIFNNUM"&" "&D55)
A56: UIFN CAN | B56: UIFN CAN | C56: Canada | D56: CAN | F56: 0.0189 | G56: =IF(H56="","","UIFNNUM"&" "&D56) -> UIFNNUM CAN | H56: 233.94 | I56: 26.88
A57: UIFN CAN MOB | B57: UIFN CAN MOB | C57: Canada | D57: CAN | E57: MOB | F57: 0.0189 | G57: =IF(H57="","","UIFNNUM"&" "&D57)
A58: UIFN HUN | B58: UIFN HUN | C58: Hungary | D58: HUN | F58: 0.057 | G58: =IF(H58="","","UIFNNUM"&" "&D58) -> UIFNNUM HUN | H58: 233.94 | I58: 24.43
A59: UIFN HUN MOB | B59: UIFN HUN MOB | C59: Hungary | D59: HUN | E59: MOB | F59: 0.2131 | G59: =IF(H59="","","UIFNNUM"&" "&D59)
A60: UIFN CZE | B60: UIFN CZE | C60: Czech Republic | D60: CZE | F60: 0.0299 | G60: =IF(H60="","","UIFNNUM"&" "&D60) -> UIFNNUM CZE | H60: 233.94 | I60: 30.8
A61: UIFN CZE MOB | B61: UIFN CZE MOB | C61: Czech Republic | D61: CZE | E61: MOB | F61: 0.181 | G61: =IF(H61="","","UIFNNUM"&" "&D61)
A62: UIFN IRL | B62: UIFN IRL | C62: Ireland | D62: IRL | F62: 0.0464 | G62: =IF(H62="","","UIFNNUM"&" "&D62) -> UIFNNUM IRL | H62: 233.94 | I62: 29.75
A63: UIFN IRL MOB | B63: UIFN IRL MOB | C63: Ireland | D63: IRL | E63: MOB | F63: 0.5716 | G63: =IF(H63="","","UIFNNUM"&" "&D63)
A64: UIFN DNK | B64: UIFN DNK | C64: Denmark | D64: DNK | F64: 0.0412 | G64: =IF(H64="","","UIFNNUM"&" "&D64) -> UIFNNUM DNK | H64: 233.94 | I64: 26.88
A65: UIFN DNK MOB | B65: UIFN DNK MOB | C65: Denmark | D65: DNK | E65: MOB | F65: 0.327 | G65: =IF(H65="","","UIFNNUM"&" "&D65)
A66: UIFN ITA | B66: UIFN ITA | C66: Italy | D66: ITA | F66: 0.3336 | G66: =IF(H66="","","UIFNNUM"&" "&D66) -> UIFNNUM ITA | H66: 233.94 | I66: 16.28
A67: UIFN ITA MOB | B67: UIFN ITA MOB | C67: Italy | D67: ITA | E67: MOB | F67: 0.3336 | G67: =IF(H67="","","UIFNNUM"&" "&D67)
A68: UIFN JPN | B68: UIFN JPN | C68: Japan | D68: JPN | F68: 0.0956 | G68: =IF(H68="","","UIFNNUM"&" "&D68) -> UIFNNUM JPN | H68: 233.94 | I68: 20.35
A69: UIFN JPN MOB | B69: UIFN JPN MOB | C69: Japan | D69: JPN | E69: MOB | F69: 0.0956 | G69: =IF(H69="","","UIFNNUM"&" "&D69)
A70: UIFN EST | B70: UIFN EST | C70: Estonia | D70: EST | F70: 0.032 | G70: =IF(H70="","","UIFNNUM"&" "&D70) -> UIFNNUM EST | H70: 233.94 | I70: 26.88
A71: UIFN EST MOB | B71: UIFN EST MOB | C71: Estonia | D71: EST | E71: MOB | F71: 0.032 | G71: =IF(H71="","","UIFNNUM"&" "&D71)
A72: UIFN FIN | B72: UIFN FIN | C72: Finland | D72: FIN | F72: 0.0545 | G72: =IF(H72="","","UIFNNUM"&" "&D72) -> UIFNNUM FIN | H72: 233.94 | I72: 26.88
A73: UIFN FIN MOB | B73: UIFN FIN MOB | C73: Finland | D73: FIN | E73: MOB | F73: 0.0547 | G73: =IF(H73="","","UIFNNUM"&" "&D73)
A74: UIFN LUX | B74: UIFN LUX | C74: Luxembourg | D74: LUX | F74: 0.038 | G74: =IF(H74="","","UIFNNUM"&" "&D74) -> UIFNNUM LUX | H74: 233.94 | I74: 16.28
A75: UIFN LUX MOB | B75: UIFN LUX MOB | C75: Luxembourg | D75: LUX | E75: MOB | F75: 0.0789 | G75: =IF(H75="","","UIFNNUM"&" "&D75)
A76: UIFN DEU | B76: UIFN DEU | C76: Germany | D76: DEU | F76: 0.0286 | G76: =IF(H76="","","UIFNNUM"&" "&D76) -> UIFNNUM DEU | H76: 233.94 | I76: 26.88
A77: UIFN DEU MOB | B77: UIFN DEU MOB | C77: Germany | D77: DEU | E77: MOB | F77: 0.1405 | G77: =IF(H77="","","UIFNNUM"&" "&D77)
A78: UIFN MYS | B78: UIFN MYS | C78: Malaysia | D78: MYS | F78: 0.0816 | G78: =IF(H78="","","UIFNNUM"&" "&D78) -> UIFNNUM MYS | H78: 233.94 | I78: 24.43
A79: UIFN MYS MOB | B79: UIFN MYS MOB | C79: Malaysia | D79: MYS | E79: MOB | F79: 0.0815 | G79: =IF(H79="","","UIFNNUM"&" "&D79)
A80: UIFN HKG | B80: UIFN HKG | C80: Hong Kong | D80: HKG | F80: 0.0384 | G80: =IF(H80="","","UIFNNUM"&" "&D80) -> UIFNNUM HKG | H80: 233.94 | I80: 26.88
A81: UIFN HKG MOB | B81: UIFN HKG MOB | C81: Hong Kong | D81: HKG | E81: MOB | F81: 0.0384 | G81: =IF(H81="","","UIFNNUM"&" "&D81)
A82: UIFN ISL | B82: UIFN ISL | C82: Iceland | D82: ISL | F82: 0.0499 | G82: =IF(H82="","","UIFNNUM"&" "&D82) -> UIFNNUM ISL | H82: 233.94 | I82: 26.88
A83: UIFN ISL MOB | B83: UIFN ISL MOB | C83: Iceland | D83: ISL | E83: MOB | F83: 0.0499 | G83: =IF(H83="","","UIFNNUM"&" "&D83)
A84: UIFN NOR | B84: UIFN NOR | C84: Norway | D84: NOR | F84: 0.1298 | G84: =IF(H84="","","UIFNNUM"&" "&D84) -> UIFNNUM NOR | H84: 233.94 | I84: 16.28
A85: UIFN NOR MOB | B85: UIFN NOR MOB | C85: Norway | D85: NOR | E85: MOB | F85: 0.1298 | G85: =IF(H85="","","UIFNNUM"&" "&D85)
A86: UIFN ISR | B86: UIFN ISR | C86: Israel | D86: ISR | F86: 0.0613 | G86: =IF(H86="","","UIFNNUM"&" "&D86) -> UIFNNUM ISR | H86: 233.94 | I86: 30.8
A87: UIFN ISR MOB | B87: UIFN ISR MOB | C87: Israel | D87: ISR | E87: MOB | F87: 0.0613 | G87: =IF(H87="","","UIFNNUM"&" "&D87)
A88: UIFN LTU | B88: UIFN LTU | C88: Lithuania | D88: LTU | F88: 0.1065 | G88: =IF(H88="","","UIFNNUM"&" "&D88) -> UIFNNUM LTU | H88: 233.94 | I88: 30.8
A89: UIFN LTU MOB | B89: UIFN LTU MOB | C89: Lithuania | D89: LTU | E89: MOB | F89: 0.1065 | G89: =IF(H89="","","UIFNNUM"&" "&D89)
A90: UIFN MAC | B90: UIFN MAC | C90: Macao | D90: MAC | F90: 0.4082 | G90: =IF(H90="","","UIFNNUM"&" "&D90) -> UIFNNUM MAC | H90: 233.94 | I90: 33.875
A91: UIFN MAC MOB | B91: UIFN MAC MOB | C91: Macao | D91: MAC | E91: MOB | F91: 0.4082 | G91: =IF(H91="","","UIFNNUM"&" "&D91)
A92: UIFN NLD | B92: UIFN NLD | C92: Netherlands | D92: NLD | F92: 0.0471 | G92: =IF(H92="","","UIFNNUM"&" "&D92) -> UIFNNUM NLD | H92: 233.94 | I92: 26.88
A93: UIFN NLD MOB | B93: UIFN NLD MOB | C93: Netherlands | D93: NLD | E93: MOB | F93: 0.0471 | G93: =IF(H93="","","UIFNNUM"&" "&D93)
A94: UIFN PRT | B94: UIFN PRT | C94: Portugal | D94: PRT | F94: 0.059 | G94: =IF(H94="","","UIFNNUM"&" "&D94) -> UIFNNUM PRT | H94: 233.94 | I94: 26.88
A95: UIFN PRT MOB | B95: UIFN PRT MOB | C95: Portugal | D95: PRT | E95: MOB | F95: 0.3268 | G95: =IF(H95="","","UIFNNUM"&" "&D95)
A96: UIFN SVK | B96: UIFN SVK | C96: Slovakia | D96: SVK | F96: 0.0384 | G96: =IF(H96="","","UIFNNUM"&" "&D96) -> UIFNNUM SVK | H96: 233.94 | I96: 24.43
A97: UIFN SVK MOB | B97: UIFN SVK MOB | C97: Slovakia | D97: SVK | E97: MOB | F97: 0.1069 | G97: =IF(H97="","","UIFNNUM"&" "&D97)
A98: UIFN RUS | B98: UIFN RUS | C98: Russia | D98: RUS | F98: 0.0745 | G98: =IF(H98="","","UIFNNUM"&" "&D98) -> UIFNNUM RUS | H98: 233.94 | I98: 26.88
A99: UIFN RUS MOB | B99: UIFN RUS MOB | C99: Russia | D99: RUS | E99: MOB | F99: 0.0745 | G99: =IF(H99="","","UIFNNUM"&" "&D99)
A100: UIFN ZAF | B100: UIFN ZAF | C100: South Africa | D100: ZAF | F100: 0.1767 | G100: =IF(H100="","","UIFNNUM"&" "&D100) -> UIFNNUM ZAF | H100: 233.94 | I100: 30.8
A101: UIFN ZAF MOB | B101: UIFN ZAF MOB | C101: South Africa | D101: ZAF | E101: MOB | F101: 0.1767 | G101: =IF(H101="","","UIFNNUM"&" "&D101)
A102: UIFN SGP | B102: UIFN SGP | C102: Singapore | D102: SGP | F102: 0.0451 | G102: =IF(H102="","","UIFNNUM"&" "&D102) -> UIFNNUM SGP | H102: 233.94 | I102: 30.8
A103: UIFN SGP MOB | B103: UIFN SGP MOB | C103: Singapore | D103: SGP | E103: MOB | F103: 0.0451 | G103: =IF(H103="","","UIFNNUM"&" "&D103)
A104: UIFN ESP | B104: UIFN ESP | C104: Spain | D104: ESP | F104: 0.1106 | G104: =IF(H104="","","UIFNNUM"&" "&D104) -> UIFNNUM ESP | H104: 233.94 | I104: 16.28
A105: UIFN ESP MOB | B105: UIFN ESP MOB | C105: Spain | D105: ESP | E105: MOB | F105: 0.2593 | G105: =IF(H105="","","UIFNNUM"&" "&D105)
A106: UIFN SWE | B106: UIFN SWE | C106: Sweden | D106: SWE | F106: 0.0464 | G106: =IF(H106="","","UIFNNUM"&" "&D106) -> UIFNNUM SWE | H106: 233.94 | I106: 26.88
A107: UIFN SWE MOB | B107: UIFN SWE MOB | C107: Sweden | D107: SWE | E107: MOB | F107: 0.2963 | G107: =IF(H107="","","UIFNNUM"&" "&D107)
...

Sheet Toll Share Surcharge
B2: >> Main Menu
B4: Contact Center - Toll & Revenue Share Surcharges
B5: PILOT VACS1 Schedule
B8: All rates in USD
B9: All prices exclude VAT and apply at all times of day.
B10: 'na' indicates not available as a standard service, please see Voice Availaibility Matrix.
B11: TPM charges not applicable to Advance Toll Shared Call Usage
H14: Toll Shared Call Usage | I14: Fixed Charges Per Number
I15: Code | J15: Installation | K15: Rental
B16: Code | C16: Collecting Country | D16: ISO Code | E16: number type | F16: Originating Pricing Zone | G16: Origination | H16: Per minute | I16: Per Number | J16: One time | K16: Monthly
B17: TS ARG 810 | C17: Argentina | D17: ARG | E17: Toll Share | F17: Argentina810 | H17: 0.0238 | I17: TSNUM ARG 810 | J17: 168.43 | K17: 17.1553
B18: TS ARG 810 MOB | C18: Argentina | D18: ARG | E18: Toll Share | F18: Argentina810 | G18: MOB | H18: 0.0238
B19: TS AUS 13 | C19: Australia | D19: AUS | E19: Toll Share | F19: Australia13 | H19: 0.014 | I19: TSNUM AUS 13 | J19: 179.2 | K19: 44.8
B20: TS AUS 13 MOB | C20: Australia | D20: AUS | E20: Toll Share | F20: Australia13 | G20: MOB | H20: 0.014
B21: TS AUS 1300 | C21: Australia | D21: AUS | E21: Toll Share | F21: Australia1300 | H21: 0.014 | I21: TSNUM AUS 1300 | J21: 168.43 | K21: 17.1553
B22: TS AUS 1300 MOB | C22: Australia | D22: AUS | E22: Toll Share | F22: Australia1300 | G22: MOB | H22: 0.014
B23: TS AUT 0720 | C23: Austria | D23: AUT | E23: Toll Share | F23: Austria0720 | H23: 0 | I23: TSNUM AUT 0720 | J23: 168.43 | K23: 53.0254
B24: TS AUT 0720 MOB | C24: Austria | D24: AUT | E24: Toll Share | F24: Austria0720 | G24: MOB | H24: 0
B25: TS AUT 810-stufe3 | C25: Austria | D25: AUT | E25: Toll Share | F25: Austria810-stufe3 | H25: 0 | I25: TSNUM AUT 810-stufe3 | J25: 168.43 | K25: 17.1553
B26: TS AUT 810-stufe3 MOB | C26: Austria | D26: AUT | E26: Toll Share | F26: Austria810-stufe3 | G26: MOB | H26: 0
B27: TS AUT 810-stufe5 | C27: Austria | D27: AUT | E27: Toll Share | F27: Austria810-stufe5 | H27: 0 | I27: TSNUM AUT 810-stufe5 | J27: 168.43 | K27: 17.1553
B28: TS AUT 810-stufe5 MOB | C28: Austria | D28: AUT | E28: Toll Share | F28: Austria810-stufe5 | G28: MOB | H28: 0
B29: TS AUT 810-stufe6 | C29: Austria | D29: AUT | E29: Toll Share | F29: Austria810-stufe6 | H29: 0 | I29: TSNUM AUT 810-stufe6 | J29: 168.43 | K29: 17.1553
B30: TS AUT 810-stufe6 MOB | C30: Austria | D30: AUT | E30: Toll Share | F30: Austria810-stufe6 | G30: MOB | H30: 0
B31: TS AUT 820-stufe3 | C31: Austria | D31: AUT | E31: Toll Share | F31: Austria820-stufe3 | H31: 0 | I31: TSNUM AUT 820-stufe3 | J31: 168.43 | K31: 17.1553
B32: TS AUT 820-stufe3 MOB | C32: Austria | D32: AUT | E32: Toll Share | F32: Austria820-stufe3 | G32: MOB | H32: 0
B33: TS AUT 820-stufe4 | C33: Austria | D33: AUT | E33: Toll Share | F33: Austria820-stufe4 | H33: 0 | I33: TSNUM AUT 820-stufe4 | J33: 168.43 | K33: 17.1553
B34: TS AUT 820-stufe4 MOB | C34: Austria | D34: AUT | E34: Toll Share | F34: Austria820-stufe4 | G34: MOB | H34: 0
B35: TS BEL 070 | C35: Belgium | D35: BEL | E35: Toll Share | F35: Belgium070 | H35: 0 | I35: TSNUM BEL 070 | J35: 168.43 | K35: 53.0254
B36: TS BEL 070 MOB | C36: Belgium | D36: BEL | E36: Toll Share | F36: Belgium070 | G36: MOB | H36: 0
B37: TS BEL 078 | C37: Belgium | D37: BEL | E37: Toll Share | F37: Belgium078 | H37: 0.006 | I37: TSNUM BEL 078 | J37: 168.43 | K37: 53.0254
B38: TS BEL 078 MOB | C38: Belgium | D38: BEL | E38: Toll Share | F38: Belgium078 | G38: MOB | H38: 0.006
B39: TS BGR 070 | C39: Bulgaria | D39: BGR | E39: Toll Share | F39: Bulgaria070 | H39: 0.0414 | I39: TSNUM BGR 070 | J39: 168.43 | K39: 53.0254
B40: TS BGR 070 MOB | C40: Bulgaria | D40: BGR | E40: Toll Share | F40: Bulgaria070 | G40: MOB | H40: 0.0414
B41: TS CHN 400 | C41: China | D41: CHN | E41: Toll Share | F41: China400 | H41: 0.0651 | I41: TSNUM CHN 400 | J41: 168.43 | K41: 44.8
B42: TS CHN 400 MOB | C42: China | D42: CHN | E42: Toll Share | F42: China400 | G42: MOB | H42: 0.0651
B43: TS CZE 0810 | C43: Czech Republic | D43: CZE | E43: Toll Share | F43: CzechRepublic0810 | H43: 0.0093 | I43: TSNUM CZE 0810 | J43: 168.43 | K43: 17.1553
B44: TS CZE 0810 MOB | C44: Czech Republic | D44: CZE | E44: Toll Share | F44: CzechRepublic0810 | G44: MOB | H44: 0.0093
B45: TS DNK 701 | C45: Denmark | D45: DNK | E45: Toll Share | F45: Denmark701 | H45: 0.0024 | I45: TSNUM DNK 701 | J45: 168.43 | K45: 53.0254
B46: TS DNK 701 MOB | C46: Denmark | D46: DNK | E46: Toll Share | F46: Denmark701 | G46: MOB | H46: 0.0024
B47: TS FIN 0203 | C47: Finland | D47: FIN | E47: Toll Share | F47: Finland0203 | H47: 0 | I47: TSNUM FIN 0203 | J47: 168.43 | K47: 179.2
B48: TS FIN 0203 MOB | C48: Finland | D48: FIN | E48: Toll Share | F48: Finland0203 | G48: MOB | H48: 0
B49: TS DEU 01801 | C49: Germany | D49: DEU | E49: Toll Share | F49: Germany01801 | H49: 0 | I49: TSNUM DEU 01801 | J49: 168.43 | K49: 17.1553
B50: TS DEU 01801 MOB | C50: Germany | D50: DEU | E50: Toll Share | F50: Germany01801 | G50: MOB | H50: 0
B51: TS DEU 01803 | C51: Germany | D51: DEU | E51: Toll Share | F51: Germany01803 | H51: 0 | I51: TSNUM DEU 01803 | J51: 168.43 | K51: 53.0254
B52: TS DEU 01803 MOB | C52: Germany | D52: DEU | E52: Toll Share | F52: Germany01803 | G52: MOB | H52: 0
B53: TS DEU 01805 | C53: Germany | D53: DEU | E53: Toll Share | F53: Germany01805 | H53: 0 | I53: TSNUM DEU 01805 | J53: 168.43 | K53: 53.0254
B54: TS DEU 01805 MOB | C54: Germany | D54: DEU | E54: Toll Share | F54: Germany01805 | G54: MOB | H54: 0
B55: TS DEU 01806 | C55: Germany | D55: DEU | E55: Toll Share | F55: Germany01806 | H55: 0.0105 | I55: TSNUM DEU 01806 | J55: 168.43 | K55: 53.0254
B56: TS DEU 01806 MOB | C56: Germany | D56: DEU | E56: Toll Share | F56: Germany01806 | G56: MOB | H56: 0.0105
B57: TS GRC 801 | C57: Greece | D57: GRC | E57: Toll Share | F57: Greece801 | H57: 0.0702 | I57: TSNUM GRC 801 | J57: 168.43 | K57: 17.1553
B58: TS GRC 801 MOB | C58: Greece | D58: GRC | E58: Toll Share | F58: Greece801 | G58: MOB | H58: 0.0702
B59: TS IND 1860 | C59: India | D59: IND | E59: Toll Share | F59: India1860 | H59: 0.0405 | I59: TSNUM IND 1860 | J59: 161.28 | K59: 191.4
B60: TS IND 1860 MOB | C60: India | D60: IND | E60: Toll Share | F60: India1860 | G60: MOB | H60: 0.0405
B61: TS IRL 0818 | C61: Ireland | D61: IRL | E61: Toll Share | F61: Ireland0818 | H61: 0 | I61: TSNUM IRL 0818 | J61: 168.43 | K61: 53.0254
B62: TS IRL 0818 MOB | C62: Ireland | D62: IRL | E62: Toll Share | F62: Ireland0818 | G62: MOB | H62: 0
B63: TS IRL 1850 | C63: Ireland | D63: IRL | E63: Toll Share | F63: Ireland1850 | H63: 0.0209 | I63: TSNUM IRL 1850 | J63: 168.43 | K63: 17.1553
B64: TS IRL 1850 MOB | C64: Ireland | D64: IRL | E64: Toll Share | F64: Ireland1850 | G64: MOB | H64: 0.0209
B65: TS IRL 1890 | C65: Ireland | D65: IRL | E65: Toll Share | F65: Ireland1890 | H65: 0.0037 | I65: TSNUM IRL 1890 | J65: 168.43 | K65: 53.0254
B66: TS IRL 1890 MOB | C66: Ireland | D66: IRL | E66: Toll Share | F66: Ireland1890 | G66: MOB | H66: 0.0037
B67: TS ITA 848 | C67: Italy | D67: ITA | E67: Toll Share | F67: Italy848 | H67: 0.0139 | I67: TSNUM ITA 848 | J67: 168.43 | K67: 17.1553
B68: TS ITA 848 MOB | C68: Italy | D68: ITA | E68: Toll Share | F68: Italy848 | G68: MOB | H68: 0.0139
B69: TS NLD 0900 | C69: Netherlands | D69: NLD | E69: Toll Share | F69: Netherlands0900 | H69: 0.0227 | I69: TSNUM NLD 0900 | J69: 168.43 | K69: 56
B70: TS NLD 0900 MOB | C70: Netherlands | D70: NLD | E70: Toll Share | F70: Netherlands0900 | G70: MOB | H70: 0.0227
B71: TS NOR 0810 | C71: Norway | D71: NOR | E71: Toll Share | F71: Norway0810 | H71: 0 | I71: TSNUM NOR 0810 | J71: 168.43 | K71: 53.0254
B72: TS NOR 0810 MOB | C72: Norway | D72: NOR | E72: Toll Share | F72: Norway0810 | G72: MOB | H72: 0
B73: TS NOR 0815 | C73: Norway | D73: NOR | E73: Toll Share | F73: Norway0815 | H73: 0 | I73: TSNUM NOR 0815 | J73: 168.43 | K73: 53.0254
B74: TS NOR 0815 MOB | C74: Norway | D74: NOR | E74: Toll Share | F74: Norway0815 | G74: MOB | H74: 0
B75: TS POL 8013 | C75: Poland | D75: POL | E75: Toll Share | F75: Poland8013 | H75: 0.1627 | I75: TSNUM POL 8013 | J75: 276.7 | K75: 47.6
B76: TS POL 8013 MOB | C76: Poland | D76: POL | E76: Toll Share | F76: Poland8013 | G76: MOB | H76: 0.1627
B77: TS POL 8015 | C77: Poland | D77: POL | E77: Toll Share | F77: Poland8015 | H77: 0.1179 | I77: TSNUM POL 8015 | J77: 276.7 | K77: 47.6
B78: TS POL 8015 MOB | C78: Poland | D78: POL | E78: Toll Share | F78: Poland8015 | G78: MOB | H78: 0.1179
B79: TS PRT 707 | C79: Portugal | D79: PRT | E79: Toll Share | F79: Portugal707 | H79: 0 | I79: TSNUM PRT 707 | J79: 168.43 | K79: 53.0254
B80: TS PRT 707 MOB | C80: Portugal | D80: PRT | E80: Toll Share | F80: Portugal707 | G80: MOB | H80: 0
B81: TS PRT 808 | C81: Portugal | D81: PRT | E81: Toll Share | F81: Portugal808 | H81: 0.006 | I81: TSNUM PRT 808 | J81: 168.43 | K81: 53.0254
B82: TS PRT 808 MOB | C82: Portugal | D82: PRT | E82: Toll Share | F82: Portugal808 | G82: MOB | H82: 0.006
B83: TS SVK 0850 | C83: Slovakia | D83: SVK | E83: Toll Share | F83: Slovakia0850 | H83: 0.09 | I83: TSNUM SVK 0850 | J83: 168.43 | K83: 44.8
B84: TS SVK 0850 MOB | C84: Slovakia | D84: SVK | E84: Toll Share | F84: Slovakia0850 | G84: MOB | H84: 0.09
B85: TS ZAF 0860 | C85: South Africa | D85: ZAF | E85: Toll Share | F85: SouthAfrica0860 | H85: 0.0539 | I85: TSNUM ZAF 0860 | J85: 168.43 | K85: 53.0254
B86: TS ZAF 0860 MOB | C86: South Africa | D86: ZAF | E86: Toll Share | F86: SouthAfrica0860 | G86: MOB | H86: 0.0539
B87: TS ZAF 0861 | C87: South Africa | D87: ZAF | E87: Toll Share | F87: SouthAfrica0861 | H87: 0.0539 | I87: TSNUM ZAF 0861 | J87: 168.43 | K87: 53.0254
B88: TS ZAF 0861 MOB | C88: South Africa | D88: ZAF | E88: Toll Share | F88: SouthAfrica0861 | G88: MOB | H88: 0.0539
B89: TS ESP 901-nivel1 | C89: Spain | D89: ESP | E89: Toll Share | F89: Spain901-nivel1 | H89: 0.0026 | I89: TSNUM ESP 901-nivel1 | J89: 168.43 | K89: 53.0254
B90: TS ESP 901-nivel1 MOB | C90: Spain | D90: ESP | E90: Toll Share | F90: Spain901-nivel1 | G90: MOB | H90: 0.0026
B91: TS ESP 902-nivel1 | C91: Spain | D91: ESP | E91: Toll Share | F91: Spain902-nivel1 | H91: 0 | I91: TSNUM ESP 902-nivel1 | J91: 168.43 | K91: 53.0254
B92: TS ESP 902-nivel1 MOB | C92: Spain | D92: ESP | E92: Toll Share | F92: Spain902-nivel1 | G92: MOB | H92: 0
B93: TS ESP 902-nivel2 | C93: Spain | D93: ESP | E93: Toll Share | F93: Spain902-nivel2 | H93: 0 | I93: TSNUM ESP 902-nivel2 | J93: 168.43 | K93: 53.0254
B94: TS ESP 902-nivel2 MOB | C94: Spain | D94: ESP | E94: Toll Share | F94: Spain902-nivel2 | G94: MOB | H94: 0
B95: TS SWE 077 | C95: Sweden | D95: SWE | E95: Toll Share | F95: Sweden077 | H95: 0.0048 | I95: TSNUM SWE 077 | J95: 168.43 | K95: 53.0254
B96: TS SWE 077 MOB | C96: Sweden | D96: SWE | E96: Toll Share | F96: Sweden077 | G96: MOB | H96: 0.0048
B97: TS CHE 084x | C97: Switzerland | D97: CHE | E97: Toll Share | F97: Switzerland084x | H97: 0.0148 | I97: TSNUM CHE 084x | J97: 168.43 | K97: 53.0254
B98: TS CHE 084x MOB | C98: Switzerland | D98: CHE | E98: Toll Share | F98: Switzerland084x | G98: MOB | H98: 0.0148
B99: TS CHE 090x | C99: Switzerland | D99: CHE | E99: Toll Share | F99: Switzerland090x | H99: 0.0146 | I99: TSNUM CHE 090x | J99: 168.43 | K99: 53.0254
B100: TS CHE 090x MOB | C100: Switzerland | D100: CHE | E100: Toll Share | F100: Switzerland090x | G100: MOB | H100: 0.0146
B101: TS GBR 03XX | C101: United Kingdom | D101: GBR | E101: Toll Share | F101: UnitedKingdom03XX | H101: 0.0048 | I101: TSNUM GBR 03XX | J101: 168.43 | K101: 17.1553
B102: TS GBR 03XX MOB | C102: United Kingdom | D102: GBR | E102: Toll Share | F102: UnitedKingdom03XX | G102: MOB | H102: 0.0048
B103: TS GBR SC001 | C103: United Kingdom | D103: GBR | E103: Toll Share | F103: UnitedKingdomSC001 | H103: 0.0017 | I103: TSNUM GBR SC001 | J103: 168.43 | K103: 53.0254
B104: TS GBR SC001 MOB | C104: United Kingdom | D104: GBR | E104: Toll Share | F104: UnitedKingdomSC001 | G104: MOB | H104: 0.0017
B105: RS AUT 810-stufe3 | C105: Austria | D105: AUT | E105: Revenue Share international | F105: Austria810-stufe3 | H105: 0 | I105: RSNUM AUT 810-stufe3 | J105: 168.43 | K105: 53.0254
B106: RS AUT 810-stufe3 MOB | C106: Austria | D106: AUT | E106: Revenue Share international | F106: Austria810-stufe3 | G106: MOB | H106: 0
...

Sheet Country & dest. codes
B1: >> Main Menu
B3: regions & call types | G3: Business Talk Margin Tool v15.38
B6: region by country | K6: list of regions | N6: list of call types
B7: country | C7: region | D7: customer-specific region | E7: billing country code | F7: ISO-3 country code | G7: ISO-2 country code | H7: country (repeated for VLOOKUPs) | K7: region | L7: description | N7: call type | O7: description
B8: Afghanistan | C8: RoW 2 | E8: AFG | F8: AFG | G8: AF | H8: Afghanistan | K8: Eur 1 | L8: major Europe | N8: fixed | O8: calls to fixed lines
B9: Albania | C9: Eur 2 | E9: ALB | F9: ALB | G9: AL | H9: Albania | K9: Eur 2 | L9: minor Europe | N9: mobile | O9: calls to mobiles
B10: Algeria | C10: RoW 2 | E10: DZA | F10: DZA | G10: DZ | H10: Algeria | K10: NAM | L10: North America | N10: NGN | O10: calls to non-geographic numbers (e.g. toll free, shared cost)
B11: All other routes | C11: RoW 2 | E11: AOR | F11: na | G11: na | H11: All other routes | K11: LAM | L11: Latin America | N11: on-net | O11: on-net calls between customer sites
B12: American Samoa | C12: RoW 2 | E12: ASM | F12: ASM | G12: AS | H12: American Samoa | K12: Asia 1 | L12: major Asia | N12: access | O12: SA Surcharge
B13: Andorra | C13: Eur 2 | E13: AND | F13: AND | G13: AD | H13: Andorra | K13: Asia 2 | L13: minor Asia | N13: ISDN | O13: international ISDN calls
B14: Angola | C14: RoW 2 | E14: AGO | F14: AGO | G14: AO | H14: Angola | K14: RoW 1 | L14: major Rest Of World
B15: Anguilla | C15: RoW 2 | E15: AIA | F15: AIA | G15: AI | H15: Anguilla | K15: RoW 2 | L15: minor Rest Of World
B16: Antarctica | C16: RoW 2 | E16: ATA | F16: ATA | G16: AQ | H16: Antarctica | K16: NGN | L16: non-geographic number
B17: Antigua & Barbuda | C17: RoW 2 | E17: ATG | F17: ATG | G17: AG | H17: Antigua & Barbuda | K17: Satellite | L17: satellite
B18: Argentina | C18: LAM | E18: ARG | F18: ARG | G18: AR | H18: Argentina
B19: Armenia | C19: RoW 1 | E19: ARM | F19: ARM | G19: AM | H19: Armenia
B20: Aruba | C20: RoW 2 | E20: ABW | F20: ABW | G20: AW | H20: Aruba
B21: Ascension Is | C21: RoW 2 | E21: ASC | F21: ASC | G21: AC | H21: Ascension Is
B22: Australia | C22: Asia 1 | E22: AUS | F22: AUS | G22: AU | H22: Australia
B23: Austria | C23: Eur 1 | E23: AUT | F23: AUT | G23: AT | H23: Austria
B24: Azerbaijan | C24: Eur 2 | E24: AZE | F24: AZE | G24: AZ | H24: Azerbaijan
B25: Bahamas | C25: RoW 2 | E25: BHS | F25: BHS | G25: BS | H25: Bahamas
B26: Bahrain | C26: RoW 1 | E26: BHR | F26: BHR | G26: BH | H26: Bahrain
B27: Bangladesh | C27: RoW 2 | E27: BGD | F27: BGD | G27: BD | H27: Bangladesh
B28: Barbados | C28: RoW 2 | E28: BRB | F28: BRB | G28: BB | H28: Barbados
B29: Belarus | C29: Eur 2 | E29: BLR | F29: BLR | G29: BY | H29: Belarus
... B61: Cuba | C61: RoW 2 | E61: CUB | F61: CUB | G61: CU | H61: Cuba
B62: Curaçao | C62: RoW 2 | E62: CUW | F62: CUW | H62: Curaçao
B63: Cyprus | C63: RoW 2 | E63: CYP | F63: CYP | G63: CY | H63: Cyprus
B64: Czech Republic | C64: Eur 2 | E64: CZE | F64: CZE | G64: CZ | H64: Czech Republic
B65: Denmark | C65: Eur 1 | E65: DNK | F65: DNK | G65: DK | H65: Denmark
B66: Diego Garcia | C66: RoW 2 | E66: IOT | F66: DGA | G66: IO | H66: Diego Garcia
B67: Djibouti | C67: RoW 2 | E67: DJI | F67: DJI | G67: DJ | H67: Djibouti
B68: Dominica | C68: RoW 2 | E68: DMA | F68: DMA | G68: DM | H68: Dominica
B69: Dominican Republic | C69: RoW 2 | E69: DOM | F69: DOM | G69: DO | H69: Dominican Republic
B70: East Timor | C70: RoW 2 | E70: TLS | F70: TLS | G70: TL | H70: East Timor
B71: Ecuador | C71: RoW 2 | E71: ECU | F71: ECU | G71: EC | H71: Ecuador
B72: Egypt | C72: RoW 1 | E72: EGY | F72: EGY | G72: EG | H72: Egypt
B73: El Salvador | C73: RoW 2 | E73: SLV | F73: SLV | G73: SV | H73: El Salvador
B74: Equatorial Guinea | C74: RoW 2 | E74: GNQ | F74: GNQ | G74: GQ | H74: Equatorial Guinea
... B198: Singapore | C198: Asia 1 | E198: SGP | F198: SGP | G198: SG | H198: Singapore
B199: Saint Maarten ( Dutch part) | C199: RoW 2 | E199: SXM | F199: SXM | H199: Saint Maarten ( Dutch part)
B200: Slovakia | C200: Eur 2 | E200: SVK | F200: SVK | G200: SK | H200: Slovakia
B201: Slovenia | C201: Eur 2 | E201: SVN | F201: SVN | G201: SI | H201: Slovenia
B202: Solomon Is | C202: RoW 2 | E202: SLB | F202: SLB | G202: SB | H202: Solomon Is
B203: Somalia | C203: RoW 2 | E203: SOM | F203: SOM | G203: SO | H203: Somalia
B204: South Africa | C204: RoW 1 | E204: ZAF | F204: ZAF | G204: ZA | H204: South Africa
B205: South Sudan | C205: RoW 2 | E205: SSD | F205: SSD | H205: South Sudan
B206: Spain and Canary Islands | C206: Eur 1 | E206: ESP | F206: ESP | G206: ES | H206: Spain and Canary Islands
B207: Sri Lanka | C207: Asia 2 | E207: LKA | F207: LKA | G207: LK | H207: Sri Lanka
B208: St Helena | C208: RoW 2 | E208: SHN | F208: SHN | G208: SH | H208: St Helena
B209: St Kitts & Nevis | C209: RoW 2 | E209: KNA | F209: KNA | G209: KN | H209: St Kitts & Nevis
B210: St Lucia | C210: RoW 2 | E210: LCA | F210: LCA | G210: LC | H210: St Lucia
B211: St Pierre & Miquelon | C211: RoW 2 | E211: SPM | F211: SPM | G211: PM | H211: St Pierre & Miquelon
B212: St Vincent & the Grenadines | C212: RoW 2 | E212: VCT | F212: VCT | G212: VC | H212: St Vincent & the Grenadines
B213: Sudan | C213: RoW 2 | E213: SDN | F213: SDN | G213: SD | H213: Sudan
B214: Suriname | C214: RoW 2 | E214: SUR | F214: SUR | G214: SR | H214: Suriname
B215: Swaziland | C215: RoW 2 | E215: SWZ | F215: SWZ | G215: SZ | H215: Swaziland
B216: Sweden | C216: Eur 1 | E216: SWE | F216: SWE | G216: SE | H216: Sweden
B217: Switzerland | C217: Eur 1 | E217: CHE | F217: CHE | G217: CH | H217: Switzerland
... B235: United Kingdom | C235: Eur 1 | E235: GBR | F235: GBR | G235: GB | H235: United Kingdom
B236: United Nations Kosovo | C236: Eur 2 | E236: XKO | F236: XKO | H236: United Nations Kosovo
B237: Uruguay | C237: RoW 2 | E237: URY | F237: URY | G237: UY | H237: Uruguay
B238: USA | C238: NAM | E238: USA | F238: USA | G238: US | H238: USA
B239: Uzbekistan | C239: Eur 2 | E239: UZB | F239: UZB | G239: UZ | H239: Uzbekistan
B240: Vanuatu | C240: RoW 2 | E240: VUT | F240: VUT | G240: VU | H240: Vanuatu
B241: Vatican City | C241: Eur 1 | E241: VAT | F241: VAT | G241: VA | H241: Vatican City
B242: Venezuela | C242: RoW 2 | E242: VEN | F242: VEN | G242: VE | H242: Venezuela
B243: Vietnam | C243: Asia 2 | E243: VNM | F243: VNM | G243: VN | H243: Vietnam
B244: VIP | C244: RoW 2 | E244: VIP | F244: na | G244: na | H244: VIP
B245: Virgin Is (UK) | C245: RoW 2 | E245: VGB | F245: VGB | G245: VG | H245: Virgin Is (UK)
B246: Virgin Is (US) | C246: RoW 2 | E246: VIR | F246: VIR | G246: VI | H246: Virgin Is (US)
B247: Wallis & Futuna | C247: RoW 2 | E247: WLF | F247: WLF | G247: WF | H247: Wallis & Futuna
B248: Yemen | C248: RoW 2 | E248: YEM | F248: YEM | G248: YE | H248: Yemen
... B250: Zimbabwe | C250: RoW 2 | E250: ZWE | F250: ZWE | G250: ZW | H250: Zimbabwe
B253: Orange Group Confidential - 25 JULY 2019

Sheet country code mapping
A1: country | B1: ISO 3 Code | C1: ISO 2 Code | G1: Count of country
A2: Afghanistan | B2: AFG | C2: AF | G2: ISO 2 Code | H2: country | I2: Total
A3: Albania | B3: ALB | C3: AL | G3: AD | H3: Andorra | I3: 1
A4: Algeria | B4: DZA | C4: DZ | G4: AE | H4: United Arab Emirates | I4: 1
A5: American Samoa | B5: ASM | C5: AS | G5: AF | H5: Afghanistan | I5: 1
A6: Andorra | B6: AND | C6: AD | G6: AG | H6: Antigua & Barbuda | I6: 1
A7: Angola | B7: AGO | C7: AO | G7: AI | H7: Anguilla | I7: 1
A8: Anguilla | B8: AIA | C8: AI | G8: AL | H8: Albania | I8: 1
A9: Antarctica | B9: ATA | C9: AQ | G9: AM | H9: Armenia | I9: 1
A10: Antigua & Barbuda | B10: ATG | C10: AG | G10: AO | H10: Angola | I10: 1
A11: Argentina | B11: ARG | C11: AR | G11: AQ | H11: Antarctica | I11: 1
A12: Armenia | B12: ARM | C12: AM | G12: AR | H12: Argentina | I12: 1
A13: Aruba | B13: ABW | C13: AW | G13: AS | H13: American Samoa | I13: 1
A14: Australia | B14: AUS | C14: AU | G14: AT | H14: Austria | I14: 1
... A18: Bahrain | B18: BHR | C18: BH | G18: BA | H18: Bosnia & Herzegovina | I18: 1
A19: Bangladesh | B19: BGD | C19: BD | H19: Bosnia/Herzegovina | I19: 1
A20: Barbados | B20: BRB | C20: BB | H20: Bosnia | I20: 1
A21: Belarus | B21: BLR | C21: BY | G21: BB | H21: Barbados | I21: 1
A22: Belgium | B22: BEL | C22: BE | G22: BD | H22: Bangladesh | I22: 1
A23: Belize | B23: BLZ | C23: BZ | G23: BE | H23: Belgium | I23: 1
A24: Benin | B24: BEN | C24: BJ | G24: BF | H24: Burkina | I24: 1
A25: Bermuda | B25: BMU | C25: BM | H25: Burkina Faso | I25: 1
A26: Bhutan | B26: BTN | C26: BT | G26: BG | H26: Bulgaria | I26: 1
A27: Bolivia | B27: BOL | C27: BO | G27: BH | H27: Bahrain | I27: 1
A28: Bonnaire St Eustache Saba | B28: BES | C28: BQ | G28: BI | H28: Burundi | I28: 1
A29: Bosnia & Herzegovina | B29: BIH | C29: BA | G29: BJ | H29: Benin | I29: 1
A30: Botswana | B30: BWA | C30: BW | G30: BM | H30: Bermuda | I30: 1
A31: Brazil | B31: BRA | C31: BR | G31: BN | H31: Brunei | I31: 1
A32: Brunei | B32: BRN | C32: BN | G32: BO | H32: Bolivia | I32: 1
A33: Bulgaria | B33: BGR | C33: BG | G33: BQ | H33: Bonaire | I33: 1
A34: Burkina Faso | B34: BFA | C34: BF | H34: Bonnaire St Eustache Saba | I34: 1
A35: Burundi | B35: BDI | C35: BI | G35: BR | H35: Brazil | I35: 1
A36: Cambodia | B36: KHM | C36: KH | G36: BS | H36: Bahamas | I36: 1
A37: Cameroon | B37: CMR | C37: CM | G37: BT | H37: Bhutan | I37: 1
A38: Canada | B38: CAN | C38: CA | G38: BW | H38: Botswana | I38: 1
A39: Cape Verde | B39: CPV | C39: CV | G39: BY | H39: Belarus | I39: 1
A40: Cayman Is | B40: CYM | C40: KY | G40: BZ | H40: Belize | I40: 1
A41: Central African Republic | B41: CAF | C41: CF | G41: CA | H41: Canada | I41: 1
A42: Chad | B42: TCD | C42: TD | G42: CD | H42: Congo Dem. Rep. | I42: 1
A43: Chile | B43: CHL | C43: CL | H43: Dem Rep of Congo | I43: 1
A44: China | B44: CHN | C44: CN | G44: CF | H44: Central African Rep | I44: 1
A45: Colombia | B45: COL | C45: CO | H45: Central African Republic | I45: 1
A46: Comoros | B46: COM | C46: KM | G46: CG | H46: Congo | I46: 1
A47: Congo | B47: COG | C47: CG | G47: CH | H47: Switzerland | I47: 1
A48: Congo Dem. Rep. | B48: COD | C48: CD | G48: CI | H48: Cote d'Ivoire | I48: 1
A49: Cook Is | B49: COK | C49: CK | H49: Ivory Coast | I49: 1
A50: Costa Rica | B50: CRI | C50: CR | G50: CK | H50: Cook Is | I50: 1
A51: Cote d'Ivoire | B51: CIV | C51: CI | H51: Cook Isl | I51: 1
A52: Croatia | B52: HRV | C52: HR | G52: CL | H52: Chile | I52: 1
A53: Cuba | B53: CUB | C53: CU | G53: CM | H53: Cameroon | I53: 1
A54: Curacao | B54: CUW | C54: CW | G54: CN | H54: China | I54: 1
A55: Cyprus | B55: CYP | C55: CY | G55: CO | H55: Colombia | I55: 1
A56: Czech Republic | B56: CZE | C56: CZ | G56: CR | H56: Costa Rica | I56: 1
A57: Denmark | B57: DNK | C57: DK | G57: CU | H57: Cuba | I57: 1
A58: Djibouti | B58: DJI | C58: DJ | H58: Guantanamo | I58: 1
A59: Dominica | B59: DMA | C59: DM | G59: CV | H59: Cape Verde | I59: 1
A60: Dominican Republic | B60: DOM | C60: DO | G60: CW | H60: Curacao | I60: 1
A61: East Timor | B61: TLS | C61: TL | G61: CY | H61: Cyprus | I61: 1
A62: Ecuador | B62: ECU | C62: EC | G62: CZ | H62: Czech Republic | I62: 1
A63: Egypt | B63: EGY | C63: EG | G63: DE | H63: Germany | I63: 1
A64: El Salvador | B64: SLV | C64: SV | G64: DJ | H64: Djibouti | I64: 1
A65: Equatorial Guinea | B65: GNQ | C65: GQ | G65: DK | H65: Denmark | I65: 1
A66: Eritrea | B66: ERI | C66: ER | G66: DM | H66: Dominica | I66: 1
A67: Estonia | B67: EST | C67: EE | G67: DO | H67: Dominican Rep | I67: 1
A68: Ethiopia | B68: ETH | C68: ET | H68: Dominican Republic | I68: 1
A69: Faeroe Is | B69: FRO | C69: FO | G69: DZ | H69: Algeria | I69: 1
A70: Falkland Is | B70: FLK | C70: FK | G70: EC | H70: Ecuador | I70: 1
A71: Fiji | B71: FJI | C71: FJ | G71: EE | H71: Estonia | I71: 1
A72: Finland | B72: FIN | C72: FI | G72: EG | H72: Egypt | I72: 1
A73: France | B73: FRA | C73: FR | G73: ER | H73: Eritrea | I73: 1
A74: French Guiana | B74: GUF | C74: GF | G74: ES | H74: Spain | I74: 1
A75: French Polynesia | B75: PYF | C75: PF | H75: Canary Is | I75: 1
A76: Gabon | B76: GAB | C76: GA | G76: ET | H76: Ethiopia | I76: 1
A77: Gambia | B77: GMB | C77: GM | G77: FI | H77: Finland | I77: 1
A78: Georgia | B78: GEO | C78: GE | G78: FJ | H78: Fiji | I78: 1
A79: Germany | B79: DEU | C79: DE | G79: FK | H79: Falkland Is | I79: 1
A80: Ghana | B80: GHA | C80: GH | H80: Falkland Isl | I80: 1
A81: Gibraltar | B81: GIB | C81: GI | G81: FM | H81: Micronesia | I81: 1
A82: Greece | B82: GRC | C82: GR | G82: FO | H82: Faeroe Is | I82: 1
A83: Greenland | B83: GRL | C83: GL | H83: Faeroe Isl | I83: 1
A84: Grenada | B84: GRD | C84: GD | G84: FR | H84: France | I84: 1
A85: Guadeloupe | B85: GLP | C85: GP | G85: GA | H85: Gabon | I85: 1
A86: Guam | B86: GUM | C86: GU | G86: GB | H86: United Kingdom | I86: 1
A87: Guatemala | B87: GTM | C87: GT | G87: GD | H87: Grenada | I87: 1
A88: Guinea | B88: GIN | C88: GN | G88: GE | H88: Georgia | I88: 1
A89: Guinea-Bissau | B89: GNB | C89: GW | G89: GF | H89: French Guiana | I89: 1
A90: Guyana | B90: GUY | C90: GY | H90: French Guyana | I90: 1
A91: Haiti | B91: HTI | C91: HT | G91: GH | H91: Ghana | I91: 1
A92: Honduras | B92: HND | C92: HN | G92: GI | H92: Gibraltar | I92: 1
A93: Hong Kong | B93: HKG | C93: HK | G93: GL | H93: Greenland | I93: 1
A94: Hungary | B94: HUN | C94: HU | G94: GM | H94: Gambia | I94: 1
A95: Iceland | B95: ISL | C95: IS | G95: GN | H95: Guinea | I95: 1
A96: India | B96: IND | C96: IN | G96: GP | H96: Guadeloupe | I96: 1
A97: Indonesia | B97: IDN | C97: ID | H97: Guadaloupe | I97: 1
A98: Iran | B98: IRN | C98: IR | G98: GQ | H98: Equatorial Guinea | I98: 1
A99: Iraq | B99: IRQ | C99: IQ | G99: GR | H99: Greece | I99: 1
A100: Ireland | B100: IRL | C100: IE | G100: GT | H100: Guatemala | I100: 1
A101: Israel | B101: ISR | C101: IL | G101: GU | H101: Guam | I101: 1
A102: Italy | B102: ITA | C102: IT | G102: GW | H102: Guinea-Bissau | I102: 1
A103: Jamaica | B103: JAM | C103: JM | G103: GY | H103: Guyana | I103: 1
...
